{"KXTRILLIONAIRE-30-EM": 90.5, "KXTAIWANLVL4-26JUL01": 3.2, "KXTAIWANLVL4-27JAN01": 14.0, "KXSWIFTKELCEWEDDINGLOCATION-30-RHO": 30.5, "KXSWIFTKELCEWEDDINGLOCATION-30-NEW": 68.5, "KXNEXTUKPM-30-NF": 6.6, "KXNEXTUKPM-30-RLOW": 3.0, "KXMUSKTRILLION-27": 82.5, "KXGTAPRICE-70": 71.5, "KXGTAPRICE-80": 30.0, "KXGTAPRICE-90": 13.5, "KXGTAPRICE-100": 9.5, "KXBOND-30-ATJ": 10.0, "KXBOND-30-JACO": 27.0, "KXBOND-30-CAL": 50.0, "KXGDPUSMAX-28-5": 52.5, "KXGREENLANDPRICE-29JAN21-NOACQ": 81.5, "KXGREENLANDPRICE-29JAN21-54B": 2.5, "KXGREENLANDPRICE-29JAN21-749B": 5.0, "KXGREENLANDPRICE-29JAN21-1049B": 1.6, "KXAMEND22-29-JAN01": 9.5, "KXUSAEXPANDTERRITORY-26JUL01": 2.4, "KXUSAEXPANDTERRITORY-27JAN01": 12.5, "KXTRUMPRESIGN": 20.0, "KXPRESPERSON-28-GNEWS": 16.5, "KXPRESPERSON-28-AOCA": 4.8, "KXPRESPERSON-28-PBUT": 2.8, "KXPRESPERSON-28-JSHA": 2.8, "KXPRESPERSON-28-KHAR": 4.8, "KXPRESPERSON-28-WMOO": 1.8, "KXPRESPERSON-28-SSMI": 0.6, "KXPRESPERSON-28-GWHI": 0.8, "KXPRESPERSON-28-ABES": 3.0, "KXPRESPERSON-28-JPRI": 2.0, "KXPRESPERSON-28-JVAN": 17.5, "KXPRESPERSON-28-TGAB": 0.5, "KXPRESPERSON-28-DTRU": 2.6, "KXPRESPERSON-28-MRUB": 19.5, "KXPRESPERSON-28-GYOU": 0.4, "KXPRESPERSON-28-DTRUJR": 0.9, "KXPRESPERSON-28-NHAL": 0.3, "KXPRESPERSON-28-RDES": 3.1, "KXPRESPERSON-28-VRAM": 0.3, "KXPRESPERSON-28-GABB": 0.3, "KXPRESPERSON-28-TWAL": 0.2, "KXPRESPERSON-28-JDIM": 0.4, "KXPRESPERSON-28-JOSS": 5.0, "KXPRESPERSON-28-MKEL": 2.3, "KXPRESPERSON-28-TCAR": 2.2, "KXPRESPARTY-2028-D": 61.5, "KXPRESPARTY-2028-R": 38.5, "KXGREENTERRITORY-29-26APR": 50.0, "KXGREENTERRITORY-29-27": 8.2, "KXGREENTERRITORY-29": 33.0, "KXCANTERRITORY-29": 14.5, "KXZELENSKYPUTIN-29-26JUL": 8.8, "KXTRUMPREMOVE": 20.5, "KXSTATE51-29-PR": 5.3, "KXSTATE51-29-CA": 3.2, "KXSTATE51-29-GL": 3.0, "KXSTATE51-29-VE": 4.8, "KXNEXTAG-29-LZEL": 24.5, "KXNEXTAG-29-MGAE": 0.3, "KXNEXTAG-29-JCLA": 0.9, "KXNEXTAG-29-ABAI": 1.6, "KXNEXTAG-29-JPIR": 4.2, "KXNEXTAG-29-MLEE": 0.3, "KXNEXTAG-29-TBLA": 47.0, "KXNEXTAG-29-KPAX": 2.8, "KXNEXTAG-29-ESCH": 0.5, "KXNEXTAG-29-HDHI": 3.4, "KXNEXTAG-29-TCRU": 0.6, "KXNEXTAG-29-AHAB": 1.1, "KXNEXTAG-29-RDES": 2.8, "KXINSURRECTION-29-27": 21.5, "KXINSURRECTION-29": 53.0, "KXIMPEACH-29-JAN20": 64.5, "KXH1B-29": 22.5, "KXGREENLAND-29-26MAY": 50.0, "KXGREENLAND-29-27": 8.1, "KXGREENLAND-29": 25.5, "KXFEDEND-29-JAN20": 8.8, "KXDOED-29-JAN20": 21.5, "KXCANAL-29": 31.5, "KXAMEND25-29": 24.5, "KXAGENCYELIM-29-USAID": 40.0, "KXFEDCHAIRCONFIRM-KWAR": 99.8, "KXFEDCHAIRCONFIRM-JSHE": 0.2, "KXFEDCHAIRCONFIRM-RRIE": 0.1, "KXFEDCHAIRCONFIRM-KHAS": 0.2, "KXVPRESNOMR-28-JDV": 7.8, "KXVPRESNOMR-28-MR": 26.0, "KXVPRESNOMR-28-EKIR": 5.7, "KXVPRESNOMD-28-GN": 5.8, "KXVPRESNOMD-28-GW": 9.8, "KXVPRESNOMD-28-PB": 6.5, "KXVPRESNOMD-28-AOC": 7.0, "KXVPRESNOMD-28-AB": 5.0, "KXVPRESNOMD-28-JOSS": 5.8, "KXPRESNOMR-28-TMAS": 1.4, "KXPRESNOMR-28-NH": 0.5, "KXPRESNOMR-28-SHS": 0.2, "KXPRESNOMR-28-GA": 0.3, "KXPRESNOMR-28-JDV": 34.5, "KXPRESNOMR-28-RDS": 4.8, "KXPRESNOMR-28-GY": 1.6, "KXPRESNOMR-28-RFK": 0.5, "KXPRESNOMR-28-VR": 0.5, "KXPRESNOMR-28-DJT": 3.5, "KXPRESNOMR-28-DJTJR": 4.8, "KXPRESNOMR-28-EM": 0.1, "KXPRESNOMR-28-BK": 0.9, "KXPRESNOMR-28-MG": 0.2, "KXPRESNOMR-28-BD": 0.3, "KXPRESNOMR-28-ES": 0.2, "KXPRESNOMR-28-JH": 0.8, "KXPRESNOMR-28-TC": 0.9, "KXPRESNOMR-28-KB": 0.3, "KXPRESNOMR-28-JT": 0.2, "KXPRESNOMR-28-MR": 29.5, "KXPRESNOMR-28-TG": 0.6, "KXPRESNOMR-28-KNOE": 0.1, "KXPRESNOMR-28-MPEN": 0.2, "KXPRESNOMR-28-STE": 0.3, "KXPRESNOMR-28-EKIR": 0.4, "KXPRESNOMR-28-TCAR": 5.7, "KXPRESNOMR-28-MTG": 1.1, "KXPRESNOMR-28-NMIN": 0.1, "KXPRESNOMR-28-TCOT": 0.3, "KXPRESNOMR-28-RPAU": 0.8, "KXPRESNOMR-28-ITRU": 1.1, "KXPRESNOMR-28-ETRU": 0.2, "KXPRESNOMR-28-PHEG": 0.3, "KXPRESNOMD-28-HBID": 0.2, "KXPRESNOMD-28-JTAL": 2.8, "KXPRESNOMD-28-RGAL": 0.9, "KXPRESNOMD-28-RKHA": 2.7, "KXPRESNOMD-28-CMUR": 0.4, "KXPRESNOMD-28-ZMAM": 0.3, "KXPRESNOMD-28-KH": 9.2, "KXPRESNOMD-28-GN": 24.5, "KXPRESNOMD-28-GW": 1.4, "KXPRESNOMD-28-JS": 4.5, "KXPRESNOMD-28-TW": 0.2, "KXPRESNOMD-28-AOC": 8.1, "KXPRESNOMD-28-MC": 0.8, "KXPRESNOMD-28-PB": 4.7, "KXPRESNOMD-28-WM": 2.8, "KXPRESNOMD-28-AB": 3.8, "KXPRESNOMD-28-RC": 0.5, "KXPRESNOMD-28-JBP": 2.5, "KXPRESNOMD-28-JF": 0.2, "KXPRESNOMD-28-RW": 0.5, "KXPRESNOMD-28-MO": 1.4, "KXPRESNOMD-28-SAS": 0.8, "KXPRESNOMD-28-MK": 3.5, "KXPRESNOMD-28-JP": 0.2, "KXPRESNOMD-28-REMA": 5.0, "KXPRESNOMD-28-JSTE": 1.3, "KXPRESNOMD-28-BOBA": 0.2, "KXPRESNOMD-28-HCLI": 0.2, "KXPRESNOMD-28-CBOO": 0.8, "KXPRESNOMD-28-LC": 0.1, "KXPRESNOMD-28-BS": 0.3, "KXPRESNOMD-28-JOSS": 7.2, "KXPRESNOMD-28-GR": 0.2, "KXPRESNOMD-28-PHI": 0.1, "KXPRESNOMD-28-LJAM": 0.1, "KXPRESNOMD-28-AKLO": 0.2, "KXPRESNOMD-28-JAM": 0.2, "KXPRESNOMD-28-ESLO": 0.3, "KXPRESNOMD-28-DJOH": 0.2, "KXPRESNOMD-28-AYAN": 0.5, "KXPRESNOMD-28-JCRO": 0.1, "KXPRESNOMD-28-BORO": 0.2, "KXPRESNOMD-28-GPLA": 1.8, "KXPRESNOMD-28-EWAR": 0.2, "KXCITRINI-28JUL01": 24.5, "KXSPACEXBANKPUBLIC-28JAN01-GSX": 93.5, "KXSPACEXBANKPUBLIC-28JAN01-MSX": 95.0, "KXSPACEXBANKPUBLIC-28JAN01-JPMX": 91.0, "KXSPACEXBANKPUBLIC-28JAN01-BOAX": 93.5, "KXSPACEXBANKPUBLIC-28JAN01-CITIX": 93.0, "KXSCOTTIESLAM-28": 6.5, "KXTRUMPBULLCASECOMBO-27DEC-26": 7.0, "KXTRUMPBEARCASECOMBO-27DEC-26": 18.0, "KXHOUSEPOPVOTEMARGIN-27NOV03-B50": 19.0, "KXTAKEOVERACQWB-27JUN30-NFLX": 3.0, "KXTAKEOVERACQWB-27JUN30-PSKY": 80.5, "KXTAKEOVERACQWB-27JUN30-NONE": 16.5, "KXIPOSPACEX-26APR01": 50.0, "KXIPOSPACEX-26MAY01": 50.0, "KXIPOSPACEX-26JUN01": 12.5, "KXIPOSPACEX-26JUL01": 78.5, "KXIPOSPACEX-26AUG01": 86.0, "KXIRANDEMOCRACY-27MAR01-T6": 7.3, "KXMOVVAREDISTRICT-26APR21-YES-P57": 0.3, "KXMOVVAREDISTRICT-26APR21-YES-P13": 0.4, "KXMOVVAREDISTRICT-26APR21-YES-P10": 0.3, "KXMOVVAREDISTRICT-26APR21-YES-P7": 0.4, "KXMOVVAREDISTRICT-26APR21-YES-P4": 14.5, "KXMOVVAREDISTRICT-26APR21-YES-P1": 1.3, "KXMOVVAREDISTRICT-26APR21-NO-P1": 0.9, "KXMOVVAREDISTRICT-26APR21-NO-P51": 0.6, "KXPRIMARYMOV-HOUSENJ11SPECIAL26-AMEJ-P63": 0.5, "KXMOVWISUPREMECOURT-26APR07-T59": 99.2, "KXMARMAD-27-DUKE": 13.0, "KXMARMAD-27-MICH": 12.0, "KXMARMAD-27-FLA": 11.5, "KXPERUPRESMATCHUP-26APR-KFUJRALI": 2.5, "KXMVESPORTSMULTIGAMEEXTENDED-S2026870172A1A2C-97CD1403092": 26.1, "KXMVECROSSCATEGORY-S2026EBB1C707093-8A47F2F5E21": 7.9, "KXMVECROSSCATEGORY-S2026BABF98C6B75-54C08017B5A": 29.3, "KXMVESPORTSMULTIGAMEEXTENDED-S2026CF3E2F3A593-B3F3FEE3D5E": 37.8, "KXMVECROSSCATEGORY-S2026644C5F68541-0E70D4706D4": 7.8, "KXMVECROSSCATEGORY-S2026E4339FA2E84-FFF79279C65": 29.3, "KXMVESPORTSMULTIGAMEEXTENDED-S20262708AC626FF-0E969B48C52": 22.9, "KXMVESPORTSMULTIGAMEEXTENDED-S2026DEDD8B4FED4-DA24B2CF4C8": 24.6, "KXMVESPORTSMULTIGAMEEXTENDED-S20265E9B408E200-52631DE7971": 12.7, "KXMVECROSSCATEGORY-S20262544DDF4CC7-CF09A567DAC": 15.7, "KXMVESPORTSMULTIGAMEEXTENDED-S202696CFE693900-BD000798FF1": 3.7, "KXMVECROSSCATEGORY-S2026A2D96099B9F-771B2AAB9C8": 3.1, "KXMVESPORTSMULTIGAMEEXTENDED-S202675CB7218EF5-76A5110D3D4": 16.8, "KXMVESPORTSMULTIGAMEEXTENDED-S2026E31DE5C1A3C-0EEA1C62B9A": 24.0, "KXMVESPORTSMULTIGAMEEXTENDED-S2026721A142DB04-4579F20BE45": 2.5, "KXMVESPORTSMULTIGAMEEXTENDED-S2026BB09EB769E7-2F60EB75F9C": 3.7, "KXMVESPORTSMULTIGAMEEXTENDED-S20269E0405B5EF0-80F637034A1": 5.3, "KXMVESPORTSMULTIGAMEEXTENDED-S20268FB8486EA73-5F0AA04D3F5": 1.2, "KXMVECROSSCATEGORY-S202634B0657D81B-5596DE2F1FC": 34.7, "KXMVECROSSCATEGORY-S20265E477A097ED-DA336BEEB47": 1.4, "KXMVECROSSCATEGORY-S20269B1DAE1E98C-D2AE56A1B83": 3.1, "KXMVESPORTSMULTIGAMEEXTENDED-S2026A9BEDD7475C-BAF4749DBA8": 4.0, "KXMVECROSSCATEGORY-S202602D2593CBC9-892AC902482": 12.7, "KXMVESPORTSMULTIGAMEEXTENDED-S2026669067CA5E3-D26CC7DCAE5": 2.1, "KXMVESPORTSMULTIGAMEEXTENDED-S20263CA73E78E59-2DFC9C3A341": 5.1, "KXMVESPORTSMULTIGAMEEXTENDED-S2026B27868BB6F4-0DC7772B739": 5.1, "KXMVESPORTSMULTIGAMEEXTENDED-S2026ECD200B93EC-28584E9AC8D": 5.6, "KXMVESPORTSMULTIGAMEEXTENDED-S2026C86348C4AE2-C7345682567": 20.5, "KXMVESPORTSMULTIGAMEEXTENDED-S202647BFC434634-F39B38AAD06": 4.0, "KXMVECROSSCATEGORY-S20263A7BBCB77EE-6A66A40AA28": 11.5, "KXMVESPORTSMULTIGAMEEXTENDED-S2026E18E742EDC8-7C951CEDB98": 50.0, "KXMVESPORTSMULTIGAMEEXTENDED-S2026410F103C158-201A5A24579": 1.7, "KXMVESPORTSMULTIGAMEEXTENDED-S20260E864DF5FC4-E5CD44382DE": 33.5, "KXMVESPORTSMULTIGAMEEXTENDED-S20269315F62DC86-F979F45C694": 22.9, "KXMVESPORTSMULTIGAMEEXTENDED-S2026DEDD8B4FED4-E4475924D99": 23.5, "KXMVESPORTSMULTIGAMEEXTENDED-S202628BD808698E-CF2A5701940": 6.7, "KXMVECROSSCATEGORY-S2026F1D2282A6E2-D2AD0303543": 13.4, "KXMVESPORTSMULTIGAMEEXTENDED-S20261F1BEA9D1BF-EB464740A6D": 2.7, "KXMVECROSSCATEGORY-S20265711EFB8706-168E9A3A1BA": 10.0, "KXMVECROSSCATEGORY-S2026142C72F09BB-3CEFB91E076": 3.8, "KXMVESPORTSMULTIGAMEEXTENDED-S202606627D51728-84799497302": 4.0, "KXMVESPORTSMULTIGAMEEXTENDED-S20263B724ACB4A7-D9307971D71": 1.3, "KXMVECROSSCATEGORY-S202620E00F9DB6A-5443C51A0CF": 7.0, "KXMVESPORTSMULTIGAMEEXTENDED-S202616CB2492571-C78363E7FB3": 21.6, "KXMVECROSSCATEGORY-S202689E7822B6BB-6CDB93E4B26": 14.0, "KXMVECROSSCATEGORY-S20267DB7F109576-40B4A1C3837": 31.5, "KXMVESPORTSMULTIGAMEEXTENDED-S2026E99661FE3F5-5A107399148": 50.0, "KXMVESPORTSMULTIGAMEEXTENDED-S2026745E1604FD9-5FC31837956": 25.3, "KXMVESPORTSMULTIGAMEEXTENDED-S2026AEF12D9EC08-0ACAE4F6A5A": 12.7, "KXMVESPORTSMULTIGAMEEXTENDED-S2026B1F1E386CD6-FFEB42A4EBA": 3.5, "KXMVECROSSCATEGORY-S2026CACB2536DE8-904FB459639": 50.0, "KXMVECROSSCATEGORY-S2026A4FE2AE10D8-CA95E6F082F": 50.0, "KXMVESPORTSMULTIGAMEEXTENDED-S2026D2AD998E8E1-D4E3F001806": 50.0, "KXMVECROSSCATEGORY-S2026132FD3D7B15-E285DC0833B": 6.0, "KXMVESPORTSMULTIGAMEEXTENDED-S20262A0395357DA-7CA7BB1DF10": 42.5, "KXMVECROSSCATEGORY-S2026F1BC27C1D88-45B004031D9": 31.5, "KXMVESPORTSMULTIGAMEEXTENDED-S2026904E04C7C6F-0368B9309F2": 50.0, "KXMVESPORTSMULTIGAMEEXTENDED-S20266385F19F06D-9A60C072C6C": 16.9, "KXMVECROSSCATEGORY-S202669E313F74F8-BD3B37436F5": 15.3, "KXMVESPORTSMULTIGAMEEXTENDED-S202686516EA49C5-A045A3D91E1": 50.0, "KXMVECROSSCATEGORY-S2026ECE0499DC3B-0E78F733A8E": 11.1, "KXMVECROSSCATEGORY-S2026CC42E221067-F04B9AC6DCA": 2.1, "KXMVESPORTSMULTIGAMEEXTENDED-S20260E864DF5FC4-B1161FF713C": 33.9, "KXMVESPORTSMULTIGAMEEXTENDED-S20266DFBEA95D2A-CEFD9A77787": 4.2, "KXMVECROSSCATEGORY-S2026BEEAD8F919C-26A6185A772": 50.0, "KXMVECROSSCATEGORY-S2026CACB2536DE8-981C563704D": 50.0, "KXMVESPORTSMULTIGAMEEXTENDED-S202693BC0B11041-1F104922095": 3.5, "KXMVECROSSCATEGORY-S20260B4C8DF7EE1-3AABBA1C51D": 50.0, "KXMVESPORTSMULTIGAMEEXTENDED-S2026E3C008C231E-434C752A297": 10.2, "KXMVESPORTSMULTIGAMEEXTENDED-S2026A7BEE392BB3-B7835EECD69": 6.5, "KXMVECROSSCATEGORY-S2026085366FC184-79E14777C19": 9.4, "KXMVECROSSCATEGORY-S20260876DE69C42-A7AC188FE86": 50.0, "KXMVESPORTSMULTIGAMEEXTENDED-S20269794B203EB3-E88F48C804E": 4.5, "KXMVESPORTSMULTIGAMEEXTENDED-S20266A284E1737C-716D0C752BC": 2.7, "KXMVESPORTSMULTIGAMEEXTENDED-S20268773DAA44AA-58D8E9BA8BB": 50.0, "KXMVESPORTSMULTIGAMEEXTENDED-S2026E5A53529B77-CECD5FA39DE": 50.0, "KXMVESPORTSMULTIGAMEEXTENDED-S202673E82C1F036-641505BCB8E": 2.6, "KXMVESPORTSMULTIGAMEEXTENDED-S2026E99E6C53B3F-9C74E1D6F7F": 32.1, "KXMVECROSSCATEGORY-S2026387EE295BC3-4E13FF0762F": 12.7, "KXMVESPORTSMULTIGAMEEXTENDED-S20261C86818ADB3-445A67EFC92": 13.4, "KXMVECROSSCATEGORY-S20261A613E3CA44-7FA68CDF991": 28.9, "KXMVESPORTSMULTIGAMEEXTENDED-S20261F1BEA9D1BF-5D49340F905": 50.0, "KXMVECROSSCATEGORY-S20266CCDACA01EA-5C6FC314288": 4.5, "KXMVECROSSCATEGORY-S20263E37C234935-CEEFAAD8521": 50.0, "KXMVECROSSCATEGORY-S20260D237C26102-E7CBA47055D": 14.0, "KXMVECROSSCATEGORY-S2026C985843E8E9-F73D16F2732": 11.0, "KXMVESPORTSMULTIGAMEEXTENDED-S2026B3F57648C61-6247D8F0E9C": 4.2, "KXMVESPORTSMULTIGAMEEXTENDED-S2026E286CB1F088-7EC2F22E40B": 2.9, "KXMVESPORTSMULTIGAMEEXTENDED-S2026EBBE71CFDA5-D9C301523C3": 4.2, "KXMVESPORTSMULTIGAMEEXTENDED-S2026B701A8BB7B0-AD798E5ADD7": 22.9, "KXMVECROSSCATEGORY-S2026E9F7108EA66-3FE871CC1A8": 2.5, "KXMVESPORTSMULTIGAMEEXTENDED-S202637CD8047F36-3848B068C0C": 7.3, "KXMVESPORTSMULTIGAMEEXTENDED-S2026F16EA598BD2-B85C3B462B5": 24.6, "KXMVESPORTSMULTIGAMEEXTENDED-S2026A62C35954DC-A0EB2767B76": 50.0, "KXMVECROSSCATEGORY-S2026466C8B85E0F-AF57B11E263": 50.0, "KXMVECROSSCATEGORY-S202638702E01B1B-453054E92B9": 14.4, "KXMVESPORTSMULTIGAMEEXTENDED-S2026F898CBEA7FC-6A31AD8A332": 14.2, "KXMVESPORTSMULTIGAMEEXTENDED-S202625D49FED78A-036621D5494": 50.0, "KXMVESPORTSMULTIGAMEEXTENDED-S202656D6F41950F-94B15C72720": 19.1, "KXMVESPORTSMULTIGAMEEXTENDED-S20260E1DBA7671A-943E2BFF38A": 3.5, "KXMVECROSSCATEGORY-S20264F5F42A754F-BFCABB9A80A": 8.3, "KXMVESPORTSMULTIGAMEEXTENDED-S20266D83ED53905-6C856A30C19": 2.9, "KXMVESPORTSMULTIGAMEEXTENDED-S20266A284E1737C-2B172EB51FC": 50.0, "KXMVECROSSCATEGORY-S202699AFAA4CB57-A4A2FDEFEE4": 21.7, "KXMVESPORTSMULTIGAMEEXTENDED-S202615C8F6215E1-80AC15FBC2F": 10.8, "KXMVECROSSCATEGORY-S20263C7071A3866-80545B97462": 50.0, "KXMVESPORTSMULTIGAMEEXTENDED-S2026997729D94E1-D5CA7F4E743": 2.4, "KXMVECROSSCATEGORY-S20268D9E9DA20C3-AEED2DF9043": 22.9, "KXMVECROSSCATEGORY-S20262C1C3C70AD3-E41FC31D717": 5.8, "KXMVECROSSCATEGORY-S2026F269EF46C49-3B72AC23A1D": 7.7, "KXMVESPORTSMULTIGAMEEXTENDED-S2026ECD200B93EC-E0FFC04999B": 5.0, "KXMVECROSSCATEGORY-S2026BB80DF22D0E-490E30BF10D": 50.0, "KXMVESPORTSMULTIGAMEEXTENDED-S20268E55F363CE8-70BDB70C247": 50.0, "KXMVECROSSCATEGORY-S2026EF6C10E4C87-6E1717D14EB": 22.9, "KXMVESPORTSMULTIGAMEEXTENDED-S2026A7E6BB41E9C-36C0582B647": 16.9, "KXMVESPORTSMULTIGAMEEXTENDED-S202618A5B56D55D-567B8B0A6FC": 21.4, "KXMVESPORTSMULTIGAMEEXTENDED-S20263B78390D84D-5FB21762510": 1.7, "KXMVESPORTSMULTIGAMEEXTENDED-S20265147F49D5C9-9DCC4E52CC2": 31.2, "KXMVECROSSCATEGORY-S202636C71C8F21F-E5B1484723D": 16.2, "KXMVESPORTSMULTIGAMEEXTENDED-S2026E868AE0FD50-5F483D1E107": 35.0, "KXMVESPORTSMULTIGAMEEXTENDED-S2026A19156EB61D-0C2B4919883": 50.0, "KXMVECROSSCATEGORY-S2026A4B1F019DC1-2A78D4B73E8": 50.0, "KXMVESPORTSMULTIGAMEEXTENDED-S2026A44A72A0C43-467A61507E3": 50.0, "KXMVESPORTSMULTIGAMEEXTENDED-S2026C62F9360719-BEA3BE372C3": 50.0, "KXMVESPORTSMULTIGAMEEXTENDED-S2026186294A5825-EE3F33A5515": 50.0, "KXMVECROSSCATEGORY-S20260688D093D11-EEFCFBA0C9E": 50.0, "KXMVECROSSCATEGORY-S20266DECF09C8F2-CB0EA32D60C": 11.5, "KXMVESPORTSMULTIGAMEEXTENDED-S2026B6A9771BB21-F823F8828EA": 50.0, "KXMVECROSSCATEGORY-S202685F8530D688-5D265863F96": 50.0, "KXMVESPORTSMULTIGAMEEXTENDED-S202612D367B88AE-19643D7C1FA": 6.2, "KXMVESPORTSMULTIGAMEEXTENDED-S2026B1F1E386CD6-7F67BF142AC": 50.0, "KXMVECROSSCATEGORY-S2026F272B6AB4E6-509AF92E0ED": 7.4, "KXMVESPORTSMULTIGAMEEXTENDED-S202618A1F1FB52A-4325BBC3A5B": 11.1, "KXMVECROSSCATEGORY-S20269D23E9BC73E-7A9B7E5D0DC": 50.0, "KXMVESPORTSMULTIGAMEEXTENDED-S202671A1A6E8C6D-3A94C825D24": 4.2, "KXMVESPORTSMULTIGAMEEXTENDED-S202693171F16B2C-B43EEAE3F5D": 2.4, "KXMVESPORTSMULTIGAMEEXTENDED-S2026E62334169D6-34D59FD4772": 50.0, "KXMVESPORTSMULTIGAMEEXTENDED-S2026E1F374038A4-1324E3A52CF": 24.3, "KXMVESPORTSMULTIGAMEEXTENDED-S20269FE7B9791BB-B14CB74E591": 27.6, "KXMVESPORTSMULTIGAMEEXTENDED-S2026AA2E2695B1F-AD250ADBDB5": 50.0, "KXMVECROSSCATEGORY-S202645F7D3A423D-33118E5A267": 50.0, "KXMVECROSSCATEGORY-S20267854ADFA3A8-13667832491": 50.0, "KXMVESPORTSMULTIGAMEEXTENDED-S2026A66109A71A0-03924C97BD5": 8.5, "KXMVESPORTSMULTIGAMEEXTENDED-S2026022A55B2B38-EE52BE14306": 16.4, "KXMVECROSSCATEGORY-S20262E3036FB83B-B4A109ECE76": 50.0, "KXMVESPORTSMULTIGAMEEXTENDED-S202631DD5A58267-F2D26ABF6D6": 14.9, "KXMVESPORTSMULTIGAMEEXTENDED-S20265B0226E4D22-FCB789B188F": 36.7, "KXMVESPORTSMULTIGAMEEXTENDED-S20267A5361D7D4C-D9530F626A6": 6.9, "KXMVECROSSCATEGORY-S2026945C3CA2B62-D7B38945E69": 7.4, "KXMVESPORTSMULTIGAMEEXTENDED-S202686516EA49C5-DCC629BEAA2": 50.0, "KXMVESPORTSMULTIGAMEEXTENDED-S2026D3354781080-8E091F9D83B": 50.0, "KXMVECROSSCATEGORY-S2026E23C7B91BF9-C0A5AF2562C": 50.0, "KXMVESPORTSMULTIGAMEEXTENDED-S2026426E5D245C8-3F64EED235C": 10.1, "KXMVECROSSCATEGORY-S2026BB80DF22D0E-50F0695DC82": 50.0, "KXMVESPORTSMULTIGAMEEXTENDED-S20266A085362944-25F8FFAA62C": 26.8, "KXMVESPORTSMULTIGAMEEXTENDED-S202672F55BF405B-E6157DE5B88": 50.0, "KXMVESPORTSMULTIGAMEEXTENDED-S2026898DF9FA000-31F4A0E21E5": 50.0, "KXMVESPORTSMULTIGAMEEXTENDED-S2026BC3893213B3-C07AFAC3008": 4.8, "KXMVECROSSCATEGORY-S20264AA47DE2E2D-D860298FCDF": 50.0, "KXMVECROSSCATEGORY-S2026C779B4017EA-A1C28597618": 22.9, "KXMVESPORTSMULTIGAMEEXTENDED-S20262E8983F2926-0EFA0EDE938": 50.0, "KXMVECROSSCATEGORY-S2026175CA9A9928-09DB3F2AB3B": 11.5, "KXMVECROSSCATEGORY-S20264D91DB9A51B-FF7E78C60E4": 50.0, "KXMVECROSSCATEGORY-S202655C5C935CE4-AE5180144BF": 5.9, "KXMVESPORTSMULTIGAMEEXTENDED-S2026B1F1E386CD6-3987BA469A7": 50.0, "KXMVESPORTSMULTIGAMEEXTENDED-S20263F4039C3DEF-0830CD4BB73": 50.0, "KXMVECROSSCATEGORY-S20263124CEAC4CB-AEDFE623078": 50.0, "KXMVECROSSCATEGORY-S202698217F6485D-337D74AA6F2": 56.5, "KXMVESPORTSMULTIGAMEEXTENDED-S202636EC1E663B9-13000D07949": 2.1, "KXMVESPORTSMULTIGAMEEXTENDED-S20267FFCDD3FF7D-35C8620F3A3": 50.0, "KXMVESPORTSMULTIGAMEEXTENDED-S20261AC3334DF64-BD37275C28B": 6.6, "KXMVESPORTSMULTIGAMEEXTENDED-S2026621C2CF9028-11731C5D9E1": 50.0, "KXMVECROSSCATEGORY-S2026387EE295BC3-174C07698D0": 50.0, "KXMVESPORTSMULTIGAMEEXTENDED-S20268EE9611C487-B1B9B47E8E3": 50.0, "KXMVESPORTSMULTIGAMEEXTENDED-S2026CD1BCA3DBC6-59EDF04B6B8": 50.0, "KXMVESPORTSMULTIGAMEEXTENDED-S2026CC77A31ACCF-908D10F9697": 50.0, "KXMVECROSSCATEGORY-S20269B66E3B89E6-6260976CA84": 6.9, "KXMVESPORTSMULTIGAMEEXTENDED-S2026BBC39271EEB-DEE8D765B2F": 50.0, "KXMVECROSSCATEGORY-S202692608C82276-BEDE93CB197": 50.0, "KXMVESPORTSMULTIGAMEEXTENDED-S20265FE447E03A3-FC27BCCCE8F": 37.8, "KXMVECROSSCATEGORY-S2026094064EC1F9-B4D56B4A0C4": 45.5, "KXMVECROSSCATEGORY-S202679A9088ED19-79007C14150": 50.0, "KXMVESPORTSMULTIGAMEEXTENDED-S2026A6B41B1C6F8-0F8FD8907E9": 50.0, "KXMVECROSSCATEGORY-S2026C35C465F5CE-C81DBB283CE": 16.2, "KXMVESPORTSMULTIGAMEEXTENDED-S20267AE21D01445-209039D618B": 50.0, "KXMVESPORTSMULTIGAMEEXTENDED-S202677268E401A5-10660B72C5F": 50.0, "KXMVESPORTSMULTIGAMEEXTENDED-S202629631A33B66-BE55A54C278": 9.0, "KXMVESPORTSMULTIGAMEEXTENDED-S2026E797A7F620F-1CFC2053EC8": 50.0, "KXMVESPORTSMULTIGAMEEXTENDED-S2026CFAB6B3F444-263589FD25F": 50.0, "KXMVESPORTSMULTIGAMEEXTENDED-S20265AA44134412-9A62C555680": 6.2, "KXMVESPORTSMULTIGAMEEXTENDED-S202649C578D446C-D5BE250BDE4": 50.0, "KXMVECROSSCATEGORY-S2026635A246A376-CC695F675A5": 4.1, "KXMVESPORTSMULTIGAMEEXTENDED-S202669E577D8DD4-9DB15BD0C28": 11.1, "KXMVECROSSCATEGORY-S20267D871D628B7-4D4F3058FA5": 1.9, "KXMVESPORTSMULTIGAMEEXTENDED-S20261CC78169160-9261236CDB1": 56.4, "KXMVECROSSCATEGORY-S202617FDDD64CC6-B6E87854180": 50.0, "KXMVECROSSCATEGORY-S202609699575158-14BBB2DF690": 3.0, "KXMVESPORTSMULTIGAMEEXTENDED-S2026556CC9D8677-35B7756701C": 50.0, "KXMVESPORTSMULTIGAMEEXTENDED-S2026EFE00B0C392-668B2D52EEA": 50.0, "KXMVECROSSCATEGORY-S2026540101E0040-B4E7B0757BD": 50.0, "KXMVECROSSCATEGORY-S2026EAB9E5CEEEB-4A2872C3896": 50.0, "KXMVESPORTSMULTIGAMEEXTENDED-S2026D6B52419F4C-A14775E246E": 50.0, "KXMVESPORTSMULTIGAMEEXTENDED-S202658B4EF4AE2B-D75C4477BE9": 50.0, "KXMVECROSSCATEGORY-S202608219744927-8D5AA1B8E6D": 50.0, "KXMVESPORTSMULTIGAMEEXTENDED-S20267E6F52B5FD8-88A5E4B40DB": 2.3, "KXMVESPORTSMULTIGAMEEXTENDED-S202663CDA391DA4-B1CB1C69137": 50.0, "KXMVECROSSCATEGORY-S202638CD4067933-8946BD30725": 50.0, "KXMVECROSSCATEGORY-S2026B29F580A910-76CF79C8177": 50.8, "KXMVESPORTSMULTIGAMEEXTENDED-S20263702F3C9A02-DC7D976841D": 50.0, "KXMVESPORTSMULTIGAMEEXTENDED-S2026A8D066F212D-684F02FAA20": 2.5, "KXMVESPORTSMULTIGAMEEXTENDED-S20261AA96124C05-CEFF1A65E03": 27.5, "KXMVESPORTSMULTIGAMEEXTENDED-S20269598AD69E2A-4825E42FB90": 50.0, "KXMVECROSSCATEGORY-S20267B69563B88D-28C5CEAD98D": 19.1, "KXMVESPORTSMULTIGAMEEXTENDED-S20269DA84C68E61-DAC5846CACF": 1.4, "KXMVECROSSCATEGORY-S202600CCD95E071-195C64468C7": 7.4, "KXMVECROSSCATEGORY-S20262F4C845CE5C-E273537F85C": 50.0, "KXMVECROSSCATEGORY-S20267E91F56AA30-03367662A26": 50.0, "KXMVECROSSCATEGORY-S2026ECA886FB511-62F0BDB0F64": 50.0, "KXMVESPORTSMULTIGAMEEXTENDED-S2026B8D9AC50F6F-D5C9D980924": 50.0, "KXMVESPORTSMULTIGAMEEXTENDED-S20260A139253E22-DFF0A26B0CA": 25.8, "KXMVESPORTSMULTIGAMEEXTENDED-S20268FB8486EA73-4C047F78319": 50.0, "KXMVECROSSCATEGORY-S20268DB08576293-F73D30EFCBB": 50.0, "KXMVESPORTSMULTIGAMEEXTENDED-S2026DD51E28AB7E-06337737089": 50.0, "KXMVESPORTSMULTIGAMEEXTENDED-S20268AF972DFD26-C019BE6C544": 5.5, "KXMVESPORTSMULTIGAMEEXTENDED-S20260BA51A2E403-227E3C08756": 50.0, "KXMVESPORTSMULTIGAMEEXTENDED-S2026DDE09928A25-3F894F2894A": 7.9, "KXMVESPORTSMULTIGAMEEXTENDED-S2026C2FA0B2EF58-8ADD08C4DE1": 50.0, "KXMVESPORTSMULTIGAMEEXTENDED-S2026D59C6FAE69C-6A1810D12CC": 50.0, "KXMVESPORTSMULTIGAMEEXTENDED-S20267FFCDD3FF7D-30688947F11": 50.0, "KXMVECROSSCATEGORY-S2026F5C9D3C703F-03D9828E638": 21.5, "KXMVESPORTSMULTIGAMEEXTENDED-S20267B01D05DC2E-0B2EE380F81": 50.0, "KXMVESPORTSMULTIGAMEEXTENDED-S20267B4957D5F95-AF8C8CA66B1": 32.5, "KXMVESPORTSMULTIGAMEEXTENDED-S2026201DD645332-1B0DB23A2F7": 50.0, "KXMVESPORTSMULTIGAMEEXTENDED-S2026CE4BDFA2B48-66DF6AC01FC": 1.7, "KXMVECROSSCATEGORY-S202673B558E222B-6D8D571E55F": 8.4, "KXMVESPORTSMULTIGAMEEXTENDED-S2026E676C3F29C5-73A798332B2": 50.0, "KXMVECROSSCATEGORY-S2026004AE53D9D0-C0645CB7EAA": 5.7, "KXMVESPORTSMULTIGAMEEXTENDED-S2026AB86BA9E1BB-43D48B9CB1B": 17.5, "KXMVESPORTSMULTIGAMEEXTENDED-S2026D2AD998E8E1-420B4311BFD": 50.0, "KXMVESPORTSMULTIGAMEEXTENDED-S2026E0C17F5E3BF-AE9B0857EBE": 50.0, "KXMVECROSSCATEGORY-S202663CD204CF46-B63A461404B": 50.0, "KXMVESPORTSMULTIGAMEEXTENDED-S20267BD4FD785C2-416DDA4DB97": 50.0, "KXMVESPORTSMULTIGAMEEXTENDED-S20260ADD607BD20-E14BF9F026D": 50.0, "KXMVESPORTSMULTIGAMEEXTENDED-S202656C44803510-E3FBBC66EAB": 3.8, "KXMVESPORTSMULTIGAMEEXTENDED-S2026116CEBBD0FF-EAC45BF447A": 18.9, "KXMVESPORTSMULTIGAMEEXTENDED-S2026CE50039E0C1-C87C30364E3": 50.0, "KXMVESPORTSMULTIGAMEEXTENDED-S2026B3A3F2D002A-A500C616F88": 50.0, "KXMVESPORTSMULTIGAMEEXTENDED-S20267E6F52B5FD8-F33A149DD97": 50.0, "KXMVECROSSCATEGORY-S202682F43D0EB71-B5BB82804AB": 50.0, "KXMVESPORTSMULTIGAMEEXTENDED-S2026E78A4D93093-EDD834086EA": 50.0, "KXMVESPORTSMULTIGAMEEXTENDED-S2026E2A18AFF54C-1A07F1A1E60": 50.0, "KXMVESPORTSMULTIGAMEEXTENDED-S20269DE6D4972DD-EE0ECB49C78": 50.0, "KXMVESPORTSMULTIGAMEEXTENDED-S2026E0DF5E1A127-1E8F2190170": 2.0, "KXMVESPORTSMULTIGAMEEXTENDED-S20269017CBEDC27-D86BF069C2F": 50.0, "KXMVESPORTSMULTIGAMEEXTENDED-S2026C732E648FC8-7E37265C92A": 50.0, "KXMVECROSSCATEGORY-S2026F521D597342-209C3C14353": 50.0, "KXMVECROSSCATEGORY-S2026DB8D9A9BEE7-43E9BC01DA6": 50.0, "KXMVESPORTSMULTIGAMEEXTENDED-S20266041DCD8564-9CF2D9BF914": 7.0, "KXMVECROSSCATEGORY-S202668CD12A1262-0E1686B8FDF": 50.0, "KXMVESPORTSMULTIGAMEEXTENDED-S2026875C75B4F34-2F54BFF9EA2": 50.0, "KXMVECROSSCATEGORY-S20260C5C5393BAC-2221755FD4D": 50.0, "KXMVESPORTSMULTIGAMEEXTENDED-S20266E9C6A41F9F-CC3598E85A5": 50.0, "KXMVESPORTSMULTIGAMEEXTENDED-S2026416E43D783E-2F0C267D4E5": 50.0, "KXMVESPORTSMULTIGAMEEXTENDED-S2026728C96AB380-8386BBC6336": 12.5, "KXMVESPORTSMULTIGAMEEXTENDED-S2026612E8A9CDE4-B9233666900": 36.7, "KXMVESPORTSMULTIGAMEEXTENDED-S2026B2E1BB03CB2-5B8E6919C63": 50.0, "KXMVECROSSCATEGORY-S2026C7D9010016B-C4C96BCADA9": 50.0, "KXMVESPORTSMULTIGAMEEXTENDED-S202688CA0721744-4D882B85390": 50.0, "KXMVECROSSCATEGORY-S2026A6B222B8A38-8BA29B6DFBD": 19.7, "KXMVECROSSCATEGORY-S20260010B4AAAE4-47F6915B69F": 2.2, "KXMVESPORTSMULTIGAMEEXTENDED-S20268FB8486EA73-4BD78EA358F": 50.0, "KXMVECROSSCATEGORY-S2026D8672FA84CD-3C043535B61": 50.0, "KXMVECROSSCATEGORY-S2026FCC6F59BFF3-92C2504A077": 50.0, "KXMVECROSSCATEGORY-S2026F7AC2381214-81A87F5E4DD": 50.0, "KXMVECROSSCATEGORY-S20263D987C7AE7D-6E18E0C5D30": 15.0, "KXMVESPORTSMULTIGAMEEXTENDED-S20268C6A518FA03-4853B89F23D": 50.0, "KXMVESPORTSMULTIGAMEEXTENDED-S202664ED89DB0A4-8898DCC3180": 4.2, "KXMVECROSSCATEGORY-S20261EB818DC0FD-C413A3F2348": 3.9, "KXMVECROSSCATEGORY-S2026C8E724B8F5B-B6FF342D087": 50.0, "KXMVESPORTSMULTIGAMEEXTENDED-S2026F6F107CF414-EB9EA356314": 50.0, "KXMVECROSSCATEGORY-S2026B3920703460-DEFD57994E0": 50.0, "KXMVESPORTSMULTIGAMEEXTENDED-S2026AE9AD8BEC9F-620F4FBE27A": 50.0, "KXMVESPORTSMULTIGAMEEXTENDED-S2026DD51E28AB7E-107A815F8A0": 50.0, "KXMVESPORTSMULTIGAMEEXTENDED-S2026628D801A99D-8D493D746D4": 50.0, "KXMVESPORTSMULTIGAMEEXTENDED-S2026E78F0511B1E-220145A472D": 50.0, "KXMVESPORTSMULTIGAMEEXTENDED-S2026A5F41AF894F-64CB0C32912": 50.0, "KXMVECROSSCATEGORY-S2026B09ABD080CF-3B6418D9CD0": 50.0, "KXMVESPORTSMULTIGAMEEXTENDED-S2026B717D7FE592-E9B29F99DB0": 15.6, "KXMVESPORTSMULTIGAMEEXTENDED-S2026DD5EC18EF88-C0460B93DB2": 50.0, "KXMVESPORTSMULTIGAMEEXTENDED-S2026352E167F271-A8B8BD3D80F": 50.0, "KXMVECROSSCATEGORY-S2026812B3F2DDDE-FC520E4AD89": 50.0, "KXMVESPORTSMULTIGAMEEXTENDED-S20260FA3C4A6794-291A14FF5F5": 50.0, "KXMVESPORTSMULTIGAMEEXTENDED-S202660329B3608A-359BBF3C9CC": 1.8, "KXMVECROSSCATEGORY-S2026157ABF63478-830B2991CF3": 50.0, "KXMVESPORTSMULTIGAMEEXTENDED-S20260A139253E22-BCEB76CD7B3": 50.0, "KXMVESPORTSMULTIGAMEEXTENDED-S202652D43741D92-920B77CC1FC": 50.0, "KXMVESPORTSMULTIGAMEEXTENDED-S20264D014D8FAE6-A48D8C6B15E": 50.0, "KXMVESPORTSMULTIGAMEEXTENDED-S2026232F45FDE0A-FC103D89CBF": 50.0, "KXMVESPORTSMULTIGAMEEXTENDED-S2026F43A2BA6EB0-AB50A35B59C": 50.0, "KXMVECROSSCATEGORY-S2026D4CAE3A5A8E-29B3DE5955F": 50.0, "KXMVECROSSCATEGORY-S2026B60A993FA9A-C621DD64D88": 50.0, "KXMVESPORTSMULTIGAMEEXTENDED-S2026AEF4F558A11-68D1713F01F": 50.0, "KXMVESPORTSMULTIGAMEEXTENDED-S20265867EF8C1F0-D8F31596EBA": 18.1, "KXMVESPORTSMULTIGAMEEXTENDED-S20268F8057848FC-E395B0566FC": 50.0, "KXMVESPORTSMULTIGAMEEXTENDED-S2026FBAF5F046C3-3C2CE1AD72A": 50.0, "KXMVECROSSCATEGORY-S2026495105E262B-6F189139E99": 50.0, "KXMVECROSSCATEGORY-S2026F7E4CC24789-01B0D5FFFAC": 50.0, "KXMVESPORTSMULTIGAMEEXTENDED-S202661CBA5C724E-BEB9DFD3EB3": 50.0, "KXMVESPORTSMULTIGAMEEXTENDED-S2026773E6F73DC4-951FD9F941C": 19.0, "KXMVESPORTSMULTIGAMEEXTENDED-S2026659302EC148-775252597C9": 50.0, "KXMVESPORTSMULTIGAMEEXTENDED-S202675E50279532-BC06B5A629D": 50.0, "KXMVECROSSCATEGORY-S2026F5C9D3C703F-E4D32C6C294": 50.0, "KXMVESPORTSMULTIGAMEEXTENDED-S202639DEF03EA26-51AC69BA9FC": 2.6, "KXMVESPORTSMULTIGAMEEXTENDED-S2026F9430838A48-98AACF20D34": 50.0, "KXMVESPORTSMULTIGAMEEXTENDED-S202685F04F88BEB-1B1DC7AEADB": 50.0, "KXMVESPORTSMULTIGAMEEXTENDED-S2026474F6A6631F-6A7A90E431A": 50.0, "KXMVECROSSCATEGORY-S20267E91F56AA30-88C9A28B632": 50.0, "KXMVECROSSCATEGORY-S20261E2A3869101-F6D35768706": 50.0, "KXMVESPORTSMULTIGAMEEXTENDED-S2026395242617F8-2421BE6D749": 50.0, "KXMVESPORTSMULTIGAMEEXTENDED-S20267C7DB03CF13-A1B97DA6D29": 17.0, "KXMVECROSSCATEGORY-S202636F6FBF9D0D-41F7460CC81": 15.3, "KXMVESPORTSMULTIGAMEEXTENDED-S202642794B23224-42907862E2D": 12.0, "KXMVESPORTSMULTIGAMEEXTENDED-S2026ED4D7130683-E407AC93EB7": 50.0, "KXMVESPORTSMULTIGAMEEXTENDED-S2026D77C96F0CEB-9122D07EA23": 15.0, "KXMVESPORTSMULTIGAMEEXTENDED-S2026D439432C59A-E41FF720BD3": 50.0, "KXMVESPORTSMULTIGAMEEXTENDED-S20269EA265B2835-FA09752FC25": 50.0, "KXMVECROSSCATEGORY-S20260A7C4E7B5A5-242227490DE": 50.0, "KXMVECROSSCATEGORY-S202633496339848-6C135739828": 50.0, "KXMVESPORTSMULTIGAMEEXTENDED-S20266C7DEFF84B2-B53E42E77FB": 16.5, "KXMVESPORTSMULTIGAMEEXTENDED-S202651908769872-FD1EACCC37D": 50.0, "KXMVECROSSCATEGORY-S2026FEDBF679E79-E55393AE7B5": 50.0, "KXMVESPORTSMULTIGAMEEXTENDED-S20267E6F52B5FD8-FF6D66EB53C": 4.5, "KXMVECROSSCATEGORY-S2026DB8D9A9BEE7-2329EA98CE0": 50.0, "KXMVECROSSCATEGORY-S202638E6CB21763-20F55C9EF23": 50.0, "KXMVESPORTSMULTIGAMEEXTENDED-S2026429A3AA33A0-6A44FB46B69": 4.0, "KXMVECROSSCATEGORY-S2026425B8418D7C-81E20573B7E": 50.0, "KXMVESPORTSMULTIGAMEEXTENDED-S20269D72BB71CE3-BD5FAF051C3": 50.0, "KXMVECROSSCATEGORY-S20264243583DCFB-41DFFB2C193": 6.8, "KXMVESPORTSMULTIGAMEEXTENDED-S2026738E090A05B-18A8E7E2732": 50.0, "KXMVESPORTSMULTIGAMEEXTENDED-S2026984F907FA50-8BE87565B4A": 50.0, "KXMVESPORTSMULTIGAMEEXTENDED-S202682F0DE9E2C5-151E4B1D3E7": 50.0, "KXMVESPORTSMULTIGAMEEXTENDED-S2026BE6D52C4301-6FF3D5D51D5": 50.0, "KXMVESPORTSMULTIGAMEEXTENDED-S20261DF2BB8B749-17D047A5BAD": 50.0, "KXMVESPORTSMULTIGAMEEXTENDED-S20265559B56A965-A2FF82F7049": 50.0, "KXMVECROSSCATEGORY-S2026945C3CA2B62-2E1AB02CE64": 50.0, "KXMVESPORTSMULTIGAMEEXTENDED-S20266124DCFA7AE-24DD3A1F562": 17.5, "KXMVESPORTSMULTIGAMEEXTENDED-S2026892BBC8383D-C9177BA4136": 50.0, "KXMVECROSSCATEGORY-S2026304BAF92C56-840302BE92A": 50.0, "KXMVESPORTSMULTIGAMEEXTENDED-S20266C94DDDFF2E-DD6A03F4A7D": 50.0, "KXMVESPORTSMULTIGAMEEXTENDED-S20266A49D5B715D-58AED8B3317": 5.9, "KXMVESPORTSMULTIGAMEEXTENDED-S2026B4B0E5B6620-1631BA97182": 50.0, "KXMVESPORTSMULTIGAMEEXTENDED-S20267A0C5227FA3-D1D0670A386": 10.8, "KXMVESPORTSMULTIGAMEEXTENDED-S2026914F0E53DAE-F964B8EC745": 50.0, "KXMVECROSSCATEGORY-S2026FC2767DEDEE-7C8AA83B91E": 50.0, "KXMVESPORTSMULTIGAMEEXTENDED-S2026773E6F73DC4-99FF23ED6E6": 50.0, "KXMVESPORTSMULTIGAMEEXTENDED-S202658954B8812E-839E8A55897": 50.0, "KXMVECROSSCATEGORY-S2026D9D6ADD346B-EE1B2243BB4": 50.0, "KXMVECROSSCATEGORY-S2026C2A0E4EAA16-7830512D780": 40.5, "KXMVECROSSCATEGORY-S2026157ABF63478-5058C7BA2ED": 50.0, "KXMVESPORTSMULTIGAMEEXTENDED-S20269AADBC7894A-DBC4D479870": 50.0, "KXMVECROSSCATEGORY-S2026425B8418D7C-EC576910F90": 22.9, "KXMVECROSSCATEGORY-S202676D6034EBD5-A03C15144E6": 40.5, "KXMVECROSSCATEGORY-S2026635A246A376-81CFA02D00D": 50.0, "KXMVECROSSCATEGORY-S202680F25F12341-6B9C972776A": 50.0, "KXMVECROSSCATEGORY-S20267A5CEAB0B3B-E16FACC0AF3": 50.0, "KXMVECROSSCATEGORY-S20269520DC5EE23-6C075460E8B": 3.4, "KXMVESPORTSMULTIGAMEEXTENDED-S2026E19C3FA83A8-D123057FBF5": 50.0, "KXMVESPORTSMULTIGAMEEXTENDED-S20267A81473B3C4-FAFAB383BF1": 50.0, "KXMVECROSSCATEGORY-S2026DB8D9A9BEE7-D55C568639D": 50.0, "KXMVESPORTSMULTIGAMEEXTENDED-S2026F930BA2DBB7-F91C2CAACC6": 50.0, "KXMVESPORTSMULTIGAMEEXTENDED-S2026CCB727B0C9A-6517424C2F3": 29.2, "KXMVESPORTSMULTIGAMEEXTENDED-S20262CDEFCFA742-02FAA1C72E8": 50.0, "KXMVESPORTSMULTIGAMEEXTENDED-S2026A857F84E914-AC9DED33B5F": 2.1, "KXMVESPORTSMULTIGAMEEXTENDED-S20264F25489C07D-9768835BA4D": 50.0, "KXMVESPORTSMULTIGAMEEXTENDED-S202676B46EC3585-02125E9E53A": 50.0, "KXMVESPORTSMULTIGAMEEXTENDED-S2026875C75B4F34-3221643FA0F": 50.0, "KXMVESPORTSMULTIGAMEEXTENDED-S20265E5591F7F99-FE042AAF236": 50.0, "KXMVECROSSCATEGORY-S2026AEE163DE6B6-24B0C2E5E8D": 50.0, "KXMVESPORTSMULTIGAMEEXTENDED-S20262CAA49C021C-499063D4820": 4.8, "KXMVECROSSCATEGORY-S202623C97DA2453-883762A549F": 7.0, "KXMVECROSSCATEGORY-S20262DF9D136F3F-4412D60A4D8": 50.0, "KXMVESPORTSMULTIGAMEEXTENDED-S2026C78F2C7A131-7BBF2A08AA0": 50.0, "KXMVESPORTSMULTIGAMEEXTENDED-S2026EA3A56E1302-CBEC4AFACFC": 50.0, "KXMVECROSSCATEGORY-S2026AC17BD97031-8A9919B6C0F": 50.0, "KXMVECROSSCATEGORY-S2026FF39A2361CD-AC94DB6877F": 50.0, "KXMVESPORTSMULTIGAMEEXTENDED-S20267E6F52B5FD8-593D88BA392": 50.0, "KXMVESPORTSMULTIGAMEEXTENDED-S2026FD20A6B84E4-76FC9440F7E": 50.0, "KXMVECROSSCATEGORY-S202673B558E222B-47B9EB557AF": 50.0, "KXMVECROSSCATEGORY-S2026AE537D9A8F8-C15281A7EDE": 22.6, "KXMVESPORTSMULTIGAMEEXTENDED-S20263F58B5A6261-5C179FA4E0F": 50.0, "KXMVECROSSCATEGORY-S20260A7C4E7B5A5-372B315463B": 50.0, "KXMVESPORTSMULTIGAMEEXTENDED-S2026914F0E53DAE-819E7DA2EB8": 2.5, "KXMVESPORTSMULTIGAMEEXTENDED-S20266C768F00914-D77EDBE9355": 15.3, "KXMVESPORTSMULTIGAMEEXTENDED-S20264B4583E5C14-6D0FB945A85": 50.0, "KXMVESPORTSMULTIGAMEEXTENDED-S20265E000E96B1C-DE0FEC668B4": 50.0, "KXMVECROSSCATEGORY-S2026243969387EF-FD59324AB90": 50.0, "KXMVECROSSCATEGORY-S2026C763B8AFAB3-7E6DED8A9D3": 50.0, "KXMVECROSSCATEGORY-S20267231DCA7A28-A21AF832130": 50.0, "KXMVESPORTSMULTIGAMEEXTENDED-S20267A0F06595EB-E2C1C9EA6F3": 50.0, "KXMVESPORTSMULTIGAMEEXTENDED-S20267650B933BD6-A1E7769BACF": 50.0, "KXMVESPORTSMULTIGAMEEXTENDED-S2026FE7FB9DB0FB-288EC40CF3D": 50.0, "KXMVESPORTSMULTIGAMEEXTENDED-S2026DA05089FEB9-2E79E2150B7": 50.0, "KXMVESPORTSMULTIGAMEEXTENDED-S2026BA3C12E7977-D14D764CA93": 3.9, "KXMVECROSSCATEGORY-S20260170A992923-027C5A9F236": 50.0, "KXMVESPORTSMULTIGAMEEXTENDED-S2026CE4BDFA2B48-A21E4AFAC2E": 50.0, "KXMVESPORTSMULTIGAMEEXTENDED-S20267F035D6A4CD-A3FBE855EAE": 50.0, "KXMVECROSSCATEGORY-S2026B4D4C4105B9-793CF6015F6": 50.0, "KXMVESPORTSMULTIGAMEEXTENDED-S2026C9584AF4EC0-E961E511F4B": 50.0, "KXMVECROSSCATEGORY-S20265872FB86358-C7410EEA4A3": 50.0, "KXMVESPORTSMULTIGAMEEXTENDED-S202679EE8D27A78-53FD756CCEC": 1.2, "KXMVECROSSCATEGORY-S20268C016F24F8F-AD19F9AD866": 50.0, "KXMVESPORTSMULTIGAMEEXTENDED-S2026FD72CCB37A7-6C3318C6347": 50.0, "KXMVECROSSCATEGORY-S202638540CBC498-8A6FD633E84": 22.9, "KXMVESPORTSMULTIGAMEEXTENDED-S20262DFC459160E-33F0584BE73": 50.0, "KXMVECROSSCATEGORY-S2026D5DCF265DEB-CBAC8F28971": 50.0, "KXMVESPORTSMULTIGAMEEXTENDED-S202609FF8553A55-B686F0374AF": 50.0, "KXMVESPORTSMULTIGAMEEXTENDED-S202610CA2CE4FB5-EDC3AA12F19": 50.0, "KXMVESPORTSMULTIGAMEEXTENDED-S2026BCB5C384794-FD0E0C952A9": 50.0, "KXMVESPORTSMULTIGAMEEXTENDED-S2026C2117CEDBDF-35DECF749D9": 50.0, "KXMVESPORTSMULTIGAMEEXTENDED-S20269B408B7702F-CEC5497BDE4": 50.0, "KXMVESPORTSMULTIGAMEEXTENDED-S2026E0DF5E1A127-208DC3302D4": 50.0, "KXMVESPORTSMULTIGAMEEXTENDED-S2026B340F0D1F11-96D5850836C": 5.0, "KXMVECROSSCATEGORY-S202638A08813663-A42CC3EB81F": 50.0, "KXMVECROSSCATEGORY-S2026A6B222B8A38-1AC1919B56C": 50.0, "KXMVESPORTSMULTIGAMEEXTENDED-S20267ACF7F23EFE-47E2CAB014D": 6.9, "KXMVECROSSCATEGORY-S2026C7D9010016B-3F8F3F30A79": 50.0, "KXMVECROSSCATEGORY-S20265A18A072A80-84816B1AD52": 50.0, "KXMVECROSSCATEGORY-S20266CD5780B3AF-4082CFE7626": 50.0, "KXMVESPORTSMULTIGAMEEXTENDED-S2026E1BF87A86BC-87216E74D6D": 50.0, "KXMVESPORTSMULTIGAMEEXTENDED-S2026460EE8F299F-E1F135E1068": 50.0, "KXMVECROSSCATEGORY-S2026BE51D8571F1-73CD0B3F71A": 50.0, "KXMVESPORTSMULTIGAMEEXTENDED-S2026C55CC9FD41C-D6CA5621926": 50.0, "KXMVESPORTSMULTIGAMEEXTENDED-S2026F1FC847950C-D9396FBDD85": 50.0, "KXMVESPORTSMULTIGAMEEXTENDED-S202604E505CA240-D086ACC95BA": 50.0, "KXMVESPORTSMULTIGAMEEXTENDED-S2026FD0B7E927A5-41BEEA51547": 50.0, "KXMVESPORTSMULTIGAMEEXTENDED-S20266D99EB22F3F-EFBE96263F6": 50.0, "KXMVESPORTSMULTIGAMEEXTENDED-S2026CD6B6DDA533-2D9F776C1F1": 50.0, "KXMVESPORTSMULTIGAMEEXTENDED-S20267FB4E049D77-55B05298FD6": 50.0, "KXMVECROSSCATEGORY-S2026B9C94C0FBBD-22773782777": 50.0, "KXMVESPORTSMULTIGAMEEXTENDED-S2026D8D0A065137-BCE271E3D66": 22.9, "KXMVESPORTSMULTIGAMEEXTENDED-S2026E8B15A29F02-B73AEFA3327": 1.4, "KXMVESPORTSMULTIGAMEEXTENDED-S2026A5846B6C9AF-5728E1B9C1D": 50.0, "KXMVESPORTSMULTIGAMEEXTENDED-S20263E7FF7F5458-2D1A54AAD74": 50.0, "KXMVESPORTSMULTIGAMEEXTENDED-S2026B78CEBDF4E8-D6DB8B3330A": 50.0, "KXMVESPORTSMULTIGAMEEXTENDED-S202671B7112D33A-CFE71DDD364": 50.0, "KXMVESPORTSMULTIGAMEEXTENDED-S20265E3D5329E92-814DD4AA54E": 50.0, "KXMVESPORTSMULTIGAMEEXTENDED-S202660A541A3D05-042EE8E7BBB": 27.7, "KXMVESPORTSMULTIGAMEEXTENDED-S20262DFC459160E-660FEF0BF61": 50.0, "KXMVESPORTSMULTIGAMEEXTENDED-S20269F8290A56BF-EDBD7A2B389": 1.3, "KXMVECROSSCATEGORY-S20261D7B3558852-126EBCDCFC9": 4.0, "KXMVESPORTSMULTIGAMEEXTENDED-S2026F8FDA40F58E-EE3A8ED44C2": 50.0, "KXMVECROSSCATEGORY-S20260A7C4E7B5A5-AFB69271E6E": 50.0, "KXMVECROSSCATEGORY-S20262A59E16FBBB-D3C9D59D461": 50.0}