{"KXTRILLIONAIRE-30-EM": 89.5, "KXTAIWANLVL4-26JUL01": 3.0, "KXTAIWANLVL4-27JAN01": 13.5, "KXSWIFTKELCEWEDDINGLOCATION-30-RHO": 32.0, "KXSWIFTKELCEWEDDINGLOCATION-30-NEW": 67.5, "KXNEXTUKPM-30-NF": 5.4, "KXNEXTUKPM-30-RLOW": 4.7, "KXMUSKTRILLION-27": 75.5, "KXGTAPRICE-70": 72.5, "KXGTAPRICE-80": 24.5, "KXGTAPRICE-90": 12.5, "KXGTAPRICE-100": 7.5, "KXBOND-30-ATJ": 9.5, "KXBOND-30-JACO": 28.5, "KXBOND-30-CAL": 42.5, "KXGDPUSMAX-28-5": 53.1, "KXGREENLANDPRICE-29JAN21-NOACQ": 82.0, "KXGREENLANDPRICE-29JAN21-54B": 1.9, "KXGREENLANDPRICE-29JAN21-749B": 5.2, "KXGREENLANDPRICE-29JAN21-1049B": 1.7, "KXAMEND22-29-JAN01": 10.1, "KXUSAEXPANDTERRITORY-26JUL01": 2.2, "KXUSAEXPANDTERRITORY-27JAN01": 11.5, "KXTRUMPRESIGN": 19.5, "KXPRESPERSON-28-GNEWS": 17.5, "KXPRESPERSON-28-AOCA": 5.3, "KXPRESPERSON-28-PBUT": 2.8, "KXPRESPERSON-28-JSHA": 3.0, "KXPRESPERSON-28-KHAR": 5.1, "KXPRESPERSON-28-WMOO": 1.7, "KXPRESPERSON-28-SSMI": 0.6, "KXPRESPERSON-28-GWHI": 0.8, "KXPRESPERSON-28-ABES": 3.2, "KXPRESPERSON-28-JPRI": 2.3, "KXPRESPERSON-28-JVAN": 17.5, "KXPRESPERSON-28-TGAB": 0.6, "KXPRESPERSON-28-DTRU": 2.5, "KXPRESPERSON-28-MRUB": 18.5, "KXPRESPERSON-28-GYOU": 0.6, "KXPRESPERSON-28-DTRUJR": 1.1, "KXPRESPERSON-28-NHAL": 0.3, "KXPRESPERSON-28-RDES": 2.0, "KXPRESPERSON-28-VRAM": 0.2, "KXPRESPERSON-28-GABB": 0.3, "KXPRESPERSON-28-TWAL": 0.1, "KXPRESPERSON-28-JDIM": 0.4, "KXPRESPERSON-28-JOSS": 6.2, "KXPRESPERSON-28-MKEL": 2.4, "KXPRESPERSON-28-TCAR": 2.2, "KXPRESPARTY-2028-D": 61.5, "KXPRESPARTY-2028-R": 37.5, "KXGREENTERRITORY-29-26APR": 50.0, "KXGREENTERRITORY-29-27": 8.3, "KXGREENTERRITORY-29": 33.5, "KXCANTERRITORY-29": 14.5, "KXTRUMPREMOVE": 24.0, "KXSTATE51-29-PR": 4.8, "KXSTATE51-29-CA": 2.4, "KXSTATE51-29-GL": 3.1, "KXSTATE51-29-VE": 1.1, "KXNEXTAG-29-LZEL": 18.5, "KXNEXTAG-29-MGAE": 0.2, "KXNEXTAG-29-JCLA": 0.9, "KXNEXTAG-29-ABAI": 1.2, "KXNEXTAG-29-JPIR": 5.0, "KXNEXTAG-29-MLEE": 0.3, "KXNEXTAG-29-TBLA": 63.5, "KXNEXTAG-29-KPAX": 1.3, "KXNEXTAG-29-ESCH": 0.6, "KXNEXTAG-29-HDHI": 2.2, "KXNEXTAG-29-TCRU": 0.5, "KXNEXTAG-29-AHAB": 0.9, "KXNEXTAG-29-RDES": 1.1, "KXINSURRECTION-29-27": 22.5, "KXINSURRECTION-29": 51.0, "KXIMPEACH-29-JAN20": 68.5, "KXH1B-29": 27.5, "KXGREENLAND-29-26MAY": 50.0, "KXGREENLAND-29-27": 8.3, "KXGREENLAND-29": 25.5, "KXFEDEND-29-JAN20": 6.5, "KXDOED-29-JAN20": 21.5, "KXCANAL-29": 31.5, "KXAMEND25-29": 30.5, "KXAGENCYELIM-29-USAID": 40.5, "KXFEDCHAIRCONFIRM-KWAR": 99.5, "KXFEDCHAIRCONFIRM-JSHE": 0.2, "KXFEDCHAIRCONFIRM-RRIE": 0.1, "KXFEDCHAIRCONFIRM-KHAS": 0.2, "KXVPRESNOMR-28-JDV": 7.5, "KXVPRESNOMR-28-MR": 26.0, "KXVPRESNOMR-28-EKIR": 6.1, "KXVPRESNOMD-28-GN": 5.9, "KXVPRESNOMD-28-GW": 9.9, "KXVPRESNOMD-28-PB": 6.3, "KXVPRESNOMD-28-AOC": 6.3, "KXVPRESNOMD-28-AB": 6.0, "KXPRESNOMR-28-TMAS": 1.2, "KXPRESNOMR-28-NH": 0.5, "KXPRESNOMR-28-SHS": 0.2, "KXPRESNOMR-28-GA": 0.3, "KXPRESNOMR-28-JDV": 36.5, "KXPRESNOMR-28-RDS": 4.5, "KXPRESNOMR-28-GY": 1.4, "KXPRESNOMR-28-RFK": 0.5, "KXPRESNOMR-28-VR": 0.5, "KXPRESNOMR-28-DJT": 3.5, "KXPRESNOMR-28-DJTJR": 5.3, "KXPRESNOMR-28-EM": 0.1, "KXPRESNOMR-28-BK": 0.9, "KXPRESNOMR-28-MG": 0.2, "KXPRESNOMR-28-BD": 0.3, "KXPRESNOMR-28-ES": 0.2, "KXPRESNOMR-28-JH": 0.8, "KXPRESNOMR-28-TC": 0.9, "KXPRESNOMR-28-KB": 0.3, "KXPRESNOMR-28-JT": 0.2, "KXPRESNOMR-28-MR": 27.5, "KXPRESNOMR-28-TG": 0.6, "KXPRESNOMR-28-KNOE": 0.1, "KXPRESNOMR-28-MPEN": 0.2, "KXPRESNOMR-28-STE": 0.3, "KXPRESNOMR-28-EKIR": 0.3, "KXPRESNOMR-28-TCAR": 7.2, "KXPRESNOMR-28-MTG": 1.1, "KXPRESNOMR-28-NMIN": 0.1, "KXPRESNOMR-28-TCOT": 0.3, "KXPRESNOMR-28-RPAU": 0.8, "KXPRESNOMR-28-ITRU": 1.1, "KXPRESNOMR-28-ETRU": 0.3, "KXPRESNOMR-28-PHEG": 0.5, "KXPRESNOMD-28-HBID": 0.1, "KXPRESNOMD-28-JTAL": 2.5, "KXPRESNOMD-28-RGAL": 0.9, "KXPRESNOMD-28-RKHA": 2.4, "KXPRESNOMD-28-CMUR": 0.3, "KXPRESNOMD-28-ZMAM": 0.5, "KXPRESNOMD-28-KH": 9.9, "KXPRESNOMD-28-GN": 24.5, "KXPRESNOMD-28-GW": 1.4, "KXPRESNOMD-28-JS": 4.5, "KXPRESNOMD-28-TW": 0.2, "KXPRESNOMD-28-AOC": 8.6, "KXPRESNOMD-28-MC": 0.8, "KXPRESNOMD-28-PB": 4.7, "KXPRESNOMD-28-WM": 2.6, "KXPRESNOMD-28-AB": 3.8, "KXPRESNOMD-28-RC": 0.5, "KXPRESNOMD-28-JBP": 2.5, "KXPRESNOMD-28-JF": 0.2, "KXPRESNOMD-28-RW": 0.5, "KXPRESNOMD-28-MO": 1.4, "KXPRESNOMD-28-SAS": 0.6, "KXPRESNOMD-28-MK": 3.4, "KXPRESNOMD-28-JP": 0.2, "KXPRESNOMD-28-REMA": 5.2, "KXPRESNOMD-28-JSTE": 1.1, "KXPRESNOMD-28-BOBA": 0.2, "KXPRESNOMD-28-HCLI": 0.2, "KXPRESNOMD-28-CBOO": 0.8, "KXPRESNOMD-28-LC": 0.1, "KXPRESNOMD-28-BS": 0.3, "KXPRESNOMD-28-JOSS": 8.1, "KXPRESNOMD-28-GR": 0.2, "KXPRESNOMD-28-PHI": 0.1, "KXPRESNOMD-28-LJAM": 0.1, "KXPRESNOMD-28-AKLO": 0.2, "KXPRESNOMD-28-JAM": 0.2, "KXPRESNOMD-28-ESLO": 0.3, "KXPRESNOMD-28-DJOH": 0.2, "KXPRESNOMD-28-AYAN": 0.5, "KXPRESNOMD-28-JCRO": 0.1, "KXPRESNOMD-28-BORO": 0.2, "KXPRESNOMD-28-GPLA": 1.0, "KXPRESNOMD-28-EWAR": 0.2, "KXCITRINI-28JUL01": 23.5, "KXSPACEXBANKPUBLIC-28JAN01-GSX": 94.0, "KXSPACEXBANKPUBLIC-28JAN01-MSX": 94.0, "KXSPACEXBANKPUBLIC-28JAN01-JPMX": 93.0, "KXSPACEXBANKPUBLIC-28JAN01-BOAX": 94.5, "KXSPACEXBANKPUBLIC-28JAN01-CITIX": 93.5, "KXSCOTTIESLAM-28": 6.5, "KXTRUMPBULLCASECOMBO-27DEC-26": 6.7, "KXTRUMPBEARCASECOMBO-27DEC-26": 15.5, "KXTAKEOVERACQWB-27JUN30-NFLX": 2.5, "KXTAKEOVERACQWB-27JUN30-PSKY": 80.5, "KXTAKEOVERACQWB-27JUN30-NONE": 16.5, "KXIPOSPACEX-26APR01": 50.0, "KXIPOSPACEX-26MAY01": 50.0, "KXIPOSPACEX-26JUN01": 10.5, "KXIPOSPACEX-26JUL01": 76.5, "KXIPOSPACEX-26AUG01": 85.5, "KXIRANDEMOCRACY-27MAR01-T6": 6.7, "KXNEXTHUNGARYPM-26MAY01-PMAG": 99.9, "KXNEXTHUNGARYPM-26MAY01-VORB": 0.1, "KXMOVVAREDISTRICT-26APR21-YES-P57": 0.3, "KXMOVVAREDISTRICT-26APR21-YES-P13": 0.3, "KXMOVVAREDISTRICT-26APR21-YES-P10": 0.8, "KXMOVVAREDISTRICT-26APR21-YES-P7": 0.3, "KXMOVVAREDISTRICT-26APR21-YES-P4": 77.5, "KXMOVVAREDISTRICT-26APR21-YES-P1": 0.6, "KXMOVVAREDISTRICT-26APR21-NO-P1": 0.5, "KXMOVVAREDISTRICT-26APR21-NO-P51": 0.6, "KXPRIMARYMOV-HOUSENJ11SPECIAL26-AMEJ-P63": 0.5, "KXMOVWISUPREMECOURT-26APR07-T59": 99.4, "KXMARMAD-27-DUKE": 13.0, "KXMARMAD-27-MICH": 12.0, "KXMARMAD-27-FLA": 11.5, "KXPERUPRES2ND-26MAR25-2-RALI": 2.3, "KXPERUPRES2ND-26MAR25-2-RPAL": 98.0, "KXMVECROSSCATEGORY-S2026EBB4CEADEDE-D105F9C61CB": 4.8, "KXMVESPORTSMULTIGAMEEXTENDED-S2026AD12C981074-9E4460E327C": 17.6, "KXMVECROSSCATEGORY-S2026FCA0A807D05-BDC35CBB488": 12.4, "KXMVESPORTSMULTIGAMEEXTENDED-S20265F48999BA3F-0DF711D3033": 17.9, "KXMVESPORTSMULTIGAMEEXTENDED-S202625D2B422284-6AAE1D092D3": 27.4, "KXMVESPORTSMULTIGAMEEXTENDED-S2026662E5DD0B25-25D673B1906": 30.8, "KXMVESPORTSMULTIGAMEEXTENDED-S20265B71B1ED47A-7016BD6A10B": 27.4, "KXMVESPORTSMULTIGAMEEXTENDED-S20264DBC8B2F4AC-2BD2C3C4971": 5.0, "KXMVESPORTSMULTIGAMEEXTENDED-S2026F0ED430ACEE-F233256C724": 3.3, "KXMVECROSSCATEGORY-S2026F6BD6C0D6C1-24C87C04D8B": 24.8, "KXMVESPORTSMULTIGAMEEXTENDED-S2026B0951B2529A-62D3F9A77AF": 24.7, "KXMVESPORTSMULTIGAMEEXTENDED-S2026C884C06824D-68C85B08C17": 39.1, "KXMVECROSSCATEGORY-S2026E01CADFF7E1-DC4A0D96E0E": 2.1, "KXMVESPORTSMULTIGAMEEXTENDED-S2026E2D1B758F7A-89DBD06D4B6": 11.1, "KXMVECROSSCATEGORY-S2026EBB4CEADEDE-FE1F836092C": 4.7, "KXMVESPORTSMULTIGAMEEXTENDED-S2026C977069AC40-A2649F43E48": 25.6, "KXMVESPORTSMULTIGAMEEXTENDED-S20262CAAE869D39-4FE8493FCEF": 16.4, "KXMVECROSSCATEGORY-S20263072F60A26E-B256B28CBDD": 9.4, "KXMVECROSSCATEGORY-S2026F4FF1EE255F-D7475FDBDB0": 10.1, "KXMVECROSSCATEGORY-S202669501AA6C88-92DA5287F8F": 17.5, "KXMVECROSSCATEGORY-S20260BDFDCC982D-230DC0CF09F": 25.3, "KXMVESPORTSMULTIGAMEEXTENDED-S2026758AC1C58BF-9FE2BB5A841": 6.2, "KXMVESPORTSMULTIGAMEEXTENDED-S20262F55B5904B5-5386AB69849": 8.6, "KXMVECROSSCATEGORY-S20265ECE1997DC9-78A6B65467A": 3.7, "KXMVESPORTSMULTIGAMEEXTENDED-S2026826F2581137-298DF1A93C6": 7.5, "KXMVECROSSCATEGORY-S20268E4C0830E27-5744BBD8D5C": 1.9, "KXMVECROSSCATEGORY-S20264073A1EA660-B5165058738": 25.3, "KXMVECROSSCATEGORY-S2026A16923D77F0-4B10D4CE0A2": 38.9, "KXMVECROSSCATEGORY-S2026C9CF64F1377-3A2E718FBFC": 39.1, "KXMVESPORTSMULTIGAMEEXTENDED-S2026BA170544589-89AE225C469": 1.8, "KXMVESPORTSMULTIGAMEEXTENDED-S2026AB3FEDF1CF0-E2195E3DA67": 2.0, "KXMVECROSSCATEGORY-S202646AAD1DD304-75ABCCB60EB": 3.0, "KXMVECROSSCATEGORY-S202665271290B11-238EAC1999D": 18.6, "KXMVESPORTSMULTIGAMEEXTENDED-S2026D445F4B3568-BD3AB113B5E": 11.9, "KXMVECROSSCATEGORY-S20269704CB67357-15930149D89": 1.4, "KXMVESPORTSMULTIGAMEEXTENDED-S2026C977069AC40-07FF9EC16A8": 25.6, "KXMVECROSSCATEGORY-S2026D49DD7C280B-CB760876A6A": 17.6, "KXMVESPORTSMULTIGAMEEXTENDED-S202678A5F363841-1471703EC0C": 13.9, "KXMVESPORTSMULTIGAMEEXTENDED-S2026ABEFCF200DD-0FD458FB879": 5.1, "KXMVESPORTSMULTIGAMEEXTENDED-S202603AC3D0FF5B-A98BE5DE8DB": 19.5, "KXMVESPORTSMULTIGAMEEXTENDED-S202699180420787-2CE1075CEC4": 2.2, "KXMVECROSSCATEGORY-S20269A1E715E0FB-D32698195DB": 2.1, "KXMVESPORTSMULTIGAMEEXTENDED-S2026B36A6371D4F-19B37E405BA": 50.0, "KXMVESPORTSMULTIGAMEEXTENDED-S20269CBD31D4FC7-B8AF00CBAA8": 50.0, "KXMVECROSSCATEGORY-S2026F9CD0FB2247-C690F23D489": 8.9, "KXMVESPORTSMULTIGAMEEXTENDED-S20265F66199B5FB-B36C8226180": 20.8, "KXMVECROSSCATEGORY-S20263E2B8CCB254-655CC8314DC": 9.8, "KXMVESPORTSMULTIGAMEEXTENDED-S20262F55B5904B5-A91046B520F": 6.0, "KXMVESPORTSMULTIGAMEEXTENDED-S2026A182BF7FDC5-CEB4B8F60D1": 32.8, "KXMVESPORTSMULTIGAMEEXTENDED-S2026AF65F5CBF6B-C01302EDAB6": 10.3, "KXMVECROSSCATEGORY-S20269B59AC6AC72-72CD223FE8A": 44.2, "KXMVECROSSCATEGORY-S20267874263905D-DBFA985D7E0": 9.6, "KXMVECROSSCATEGORY-S2026A5C92855869-C695529D52D": 13.8, "KXMVECROSSCATEGORY-S20266C4E69DFEB3-B5F6824152D": 19.6, "KXMVESPORTSMULTIGAMEEXTENDED-S202641B2DCA0769-9920DC52E65": 11.9, "KXMVESPORTSMULTIGAMEEXTENDED-S202616E940B90EC-9C31C64E6B4": 12.8, "KXMVESPORTSMULTIGAMEEXTENDED-S20260EFA7CCFECD-F8729646166": 7.0, "KXMVECROSSCATEGORY-S20263E3C9E316E7-8416A210E09": 41.0, "KXMVECROSSCATEGORY-S2026AD49909CD00-D7024632789": 10.8, "KXMVECROSSCATEGORY-S20267227E48C161-80D0D158A1B": 50.0, "KXMVECROSSCATEGORY-S20267402504BE6C-A0CC94BD82C": 7.0, "KXMVESPORTSMULTIGAMEEXTENDED-S20268FB26084627-257C2C0F042": 69.5, "KXMVESPORTSMULTIGAMEEXTENDED-S202671E6EDE7B56-0901483C497": 2.8, "KXMVESPORTSMULTIGAMEEXTENDED-S2026D8D9AF762A0-E6B544E9678": 21.3, "KXMVECROSSCATEGORY-S2026EE3DB97A33B-9ACF92FB798": 29.5, "KXMVESPORTSMULTIGAMEEXTENDED-S202680E03606E87-EBE5DC6D756": 50.0, "KXMVECROSSCATEGORY-S2026B9E2DD1222F-B696B8EF93F": 50.0, "KXMVESPORTSMULTIGAMEEXTENDED-S2026D169D220471-954BF900282": 50.0, "KXMVECROSSCATEGORY-S20268CA1F3192BD-8AF4A77782D": 50.0, "KXMVECROSSCATEGORY-S202620D8FC9926F-919D8D231A7": 1.2, "KXMVESPORTSMULTIGAMEEXTENDED-S20267C8389DF50B-EA9DB7A671C": 6.4, "KXMVECROSSCATEGORY-S2026B59F5C5C9F0-8B739948DBF": 50.0, "KXMVECROSSCATEGORY-S20263EE1D7D56BA-E39B7ACAEC0": 50.0, "KXMVESPORTSMULTIGAMEEXTENDED-S2026CBC06512800-6997D6DC808": 35.1, "KXMVESPORTSMULTIGAMEEXTENDED-S20261A9F39DEBA3-775BC5338BF": 4.0, "KXMVECROSSCATEGORY-S2026DE821878F0A-C22938929C4": 50.0, "KXMVESPORTSMULTIGAMEEXTENDED-S202664DBEBECB21-8FCFE9B805A": 50.0, "KXMVESPORTSMULTIGAMEEXTENDED-S2026AF81864DC6F-CA005637634": 7.4, "KXMVESPORTSMULTIGAMEEXTENDED-S202696D6A37B3E8-412DEB45F93": 50.0, "KXMVECROSSCATEGORY-S2026C6F81F7D1AC-C1911FDFAFB": 50.0, "KXMVECROSSCATEGORY-S20265407353F1C1-C0D0DA62874": 14.4, "KXMVECROSSCATEGORY-S202626D075AF604-BDEEA567371": 50.0, "KXMVECROSSCATEGORY-S2026EBFCBD28BD6-441004B7867": 50.0, "KXMVESPORTSMULTIGAMEEXTENDED-S2026B700268BFC9-3E49144D6CF": 12.3, "KXMVECROSSCATEGORY-S20261C73C4CE1B9-04C2AEEC5F1": 50.0, "KXMVESPORTSMULTIGAMEEXTENDED-S2026954FE40B308-6281A9C826E": 2.0, "KXMVESPORTSMULTIGAMEEXTENDED-S20261A9F39DEBA3-F23DC8678AE": 3.0, "KXMVESPORTSMULTIGAMEEXTENDED-S20267C8389DF50B-006467DB522": 7.5, "KXMVESPORTSMULTIGAMEEXTENDED-S2026400942DED84-73FF0E79E06": 50.0, "KXMVESPORTSMULTIGAMEEXTENDED-S2026C3AAA3CB07F-C4C877D8B50": 7.6, "KXMVECROSSCATEGORY-S2026D21006E1113-231E2C667C2": 50.0, "KXMVESPORTSMULTIGAMEEXTENDED-S20263D66E9E4AB6-E858FF40BDD": 50.0, "KXMVECROSSCATEGORY-S202696570783FF8-AF3371DD6A3": 50.0, "KXMVECROSSCATEGORY-S2026793C390ACB4-230256E96D7": 10.8, "KXMVECROSSCATEGORY-S202601667160E24-F2AEF8E57B9": 43.9, "KXMVESPORTSMULTIGAMEEXTENDED-S2026A61BD833AFC-E2EBE15052D": 7.0, "KXMVECROSSCATEGORY-S2026B9E2DD1222F-0987176AEF5": 50.0, "KXMVESPORTSMULTIGAMEEXTENDED-S20264AEDE15F58C-AD2FBA6A57F": 50.0, "KXMVECROSSCATEGORY-S202685BD908BCDF-76B05A8744B": 50.0, "KXMVECROSSCATEGORY-S2026D21006E1113-FD35ED0D9DD": 50.0, "KXMVECROSSCATEGORY-S2026DB82C443B4C-BE96F44E738": 65.0, "KXMVECROSSCATEGORY-S202660A4B7B28AC-B2ED9EC0FBB": 1.8, "KXMVESPORTSMULTIGAMEEXTENDED-S2026E26DC037C7B-0ED93DB104D": 50.0, "KXMVECROSSCATEGORY-S20263AF8E686BA8-121F2E1FB89": 50.0, "KXMVESPORTSMULTIGAMEEXTENDED-S20269885FF95396-1EEC29CD350": 7.0, "KXMVESPORTSMULTIGAMEEXTENDED-S2026CC3CB622B43-FCB271A980D": 59.1, "KXMVECROSSCATEGORY-S2026AA624E04145-09C2F0600AE": 50.0, "KXMVESPORTSMULTIGAMEEXTENDED-S20261EC54E5B0BB-C0DBAF7856A": 50.0, "KXMVECROSSCATEGORY-S2026243C97604CA-F06ED71EF77": 27.4, "KXMVECROSSCATEGORY-S2026A0E994E452D-3ADA99C1E46": 50.0, "KXMVECROSSCATEGORY-S2026EBB4CEADEDE-F75FE843441": 50.0, "KXMVECROSSCATEGORY-S2026E2B45DB31ED-D6511F0010E": 50.0, "KXMVESPORTSMULTIGAMEEXTENDED-S20268320EBC8E7D-1382751116F": 50.0, "KXMVESPORTSMULTIGAMEEXTENDED-S2026A015FEC5869-EE825DB7CD9": 1.7, "KXMVESPORTSMULTIGAMEEXTENDED-S2026CAB294782AF-2D0DD0DCE20": 22.7, "KXMVESPORTSMULTIGAMEEXTENDED-S202618AAC86486A-1BB93903A14": 5.7, "KXMVECROSSCATEGORY-S2026EEFE305888A-40BD03E25F3": 50.0, "KXMVECROSSCATEGORY-S202607C00737DD4-68FC76383F6": 50.0, "KXMVECROSSCATEGORY-S202661FEF691836-B00561A3B4B": 50.0, "KXMVESPORTSMULTIGAMEEXTENDED-S202657103814C54-F69FE3323AF": 8.2, "KXMVESPORTSMULTIGAMEEXTENDED-S2026896FFCFDFFE-5477504FBCB": 50.0, "KXMVESPORTSMULTIGAMEEXTENDED-S202677B4D804DAB-5CEC4E00554": 27.4, "KXMVECROSSCATEGORY-S20261395C09237C-93661BAE59D": 13.9, "KXMVESPORTSMULTIGAMEEXTENDED-S2026529D312263B-1B280BF9C6A": 6.8, "KXMVECROSSCATEGORY-S2026CBB9E00ADC1-C08444C5691": 50.0, "KXMVECROSSCATEGORY-S20265BFE897ABDA-F9DA0EB03A2": 5.0, "KXMVECROSSCATEGORY-S2026BDED3AC9479-EDA07BA6711": 50.0, "KXMVESPORTSMULTIGAMEEXTENDED-S20268CDF4DB440D-35BBD73558B": 50.0, "KXMVESPORTSMULTIGAMEEXTENDED-S202616E940B90EC-1014229D729": 50.0, "KXMVESPORTSMULTIGAMEEXTENDED-S20267C6EBEB4510-482DD8A910F": 24.8, "KXMVESPORTSMULTIGAMEEXTENDED-S2026797EF8742CE-EE2C19F515C": 3.5, "KXMVESPORTSMULTIGAMEEXTENDED-S20268D5DAAA1482-8FE5AA57BD5": 50.0, "KXMVECROSSCATEGORY-S20266D3AC800EBB-893DCFA2163": 50.0, "KXMVECROSSCATEGORY-S20262F80CA73F4F-ACBCE9E7826": 50.0, "KXMVESPORTSMULTIGAMEEXTENDED-S2026A96C72C77F6-675C2CB54A7": 50.0, "KXMVESPORTSMULTIGAMEEXTENDED-S202623B5F7F3387-340529A9810": 50.0, "KXMVESPORTSMULTIGAMEEXTENDED-S2026B44C9DF2987-DD98D70EB68": 3.4, "KXMVESPORTSMULTIGAMEEXTENDED-S20264C9749DE156-64EAD77BEFD": 22.4, "KXMVESPORTSMULTIGAMEEXTENDED-S2026D8873F1C809-F20BC2342ED": 50.0, "KXMVESPORTSMULTIGAMEEXTENDED-S2026812B527DA04-827C14481C7": 6.1, "KXMVESPORTSMULTIGAMEEXTENDED-S2026FA5A2D98712-2C36FC15796": 50.0, "KXMVESPORTSMULTIGAMEEXTENDED-S20266549CC4BFE9-6571A188B06": 50.0, "KXMVECROSSCATEGORY-S202649E708F73B6-2013ED1923F": 50.0, "KXMVESPORTSMULTIGAMEEXTENDED-S202615BA2FD21FA-FB9905130F6": 1.6, "KXMVESPORTSMULTIGAMEEXTENDED-S2026B558D111069-1C2A328A0B2": 29.5, "KXMVECROSSCATEGORY-S20261B9B526676C-A67BA6F63EF": 50.0, "KXMVESPORTSMULTIGAMEEXTENDED-S2026AC90B35D067-511ED29824C": 13.3, "KXMVESPORTSMULTIGAMEEXTENDED-S2026743F77E1854-DE1718304CB": 23.4, "KXMVESPORTSMULTIGAMEEXTENDED-S20267C8389DF50B-7061350A320": 6.0, "KXMVESPORTSMULTIGAMEEXTENDED-S2026EAD4EC4C9E5-758764EBA90": 50.0, "KXMVESPORTSMULTIGAMEEXTENDED-S202666464840EC4-0191002A688": 50.0, "KXMVESPORTSMULTIGAMEEXTENDED-S2026C50C8ECB557-1C4CF1E64D2": 50.0, "KXMVESPORTSMULTIGAMEEXTENDED-S202602E9C74B67D-BF986624983": 16.5, "KXMVESPORTSMULTIGAMEEXTENDED-S202602E9C74B67D-3A56461E438": 9.9, "KXMVECROSSCATEGORY-S2026D4F61C6D323-9A3552AAAF3": 3.5, "KXMVECROSSCATEGORY-S2026BA3194CCEA4-8F4832C1A2F": 50.0, "KXMVECROSSCATEGORY-S20269679AF2CA44-DBC41BD0359": 10.6, "KXMVESPORTSMULTIGAMEEXTENDED-S2026F1D1DE7E4E8-69D8C408140": 38.4, "KXMVESPORTSMULTIGAMEEXTENDED-S20268D5DAAA1482-07AB9066790": 50.0, "KXMVESPORTSMULTIGAMEEXTENDED-S202667F49355EF0-BC123C2D4C6": 16.5, "KXMVESPORTSMULTIGAMEEXTENDED-S2026A6D325B5B0C-699CD033188": 50.0, "KXMVECROSSCATEGORY-S20267F189CDDA0B-3B5C3C3F990": 50.0, "KXMVECROSSCATEGORY-S2026E2B6BCE1731-D889E12B518": 50.0, "KXMVESPORTSMULTIGAMEEXTENDED-S2026231039BED1B-6381678CB32": 3.4, "KXMVESPORTSMULTIGAMEEXTENDED-S202691BD29CCAE8-2DCE0CAF294": 34.9, "KXMVECROSSCATEGORY-S2026EC4EF1D455F-D3C4C4DC2CA": 50.0, "KXMVESPORTSMULTIGAMEEXTENDED-S202664DBEBECB21-6341EDF3249": 50.0, "KXMVESPORTSMULTIGAMEEXTENDED-S20269952E4085FE-6CB135E6659": 10.8, "KXMVECROSSCATEGORY-S202654492A630E4-51143B2AF13": 50.0, "KXMVECROSSCATEGORY-S2026A0E994E452D-3A9AA975A1C": 50.0, "KXMVESPORTSMULTIGAMEEXTENDED-S20265A0BFF6382F-5E61021A88D": 50.0, "KXMVECROSSCATEGORY-S20262A2D34B7C56-EF70786E4F3": 50.0, "KXMVECROSSCATEGORY-S2026996A8581109-BAA992E5BC4": 50.0, "KXMVECROSSCATEGORY-S20261EC1764D1CF-AEC9923FCCF": 39.6, "KXMVECROSSCATEGORY-S20261E74F54ACA2-014F4106CFA": 50.0, "KXMVECROSSCATEGORY-S20261143EE05E6B-DFD82A9BB45": 47.1, "KXMVECROSSCATEGORY-S2026D49920CD7B4-66F8B4E7C91": 50.0, "KXMVESPORTSMULTIGAMEEXTENDED-S2026D6A5F3C756E-AC718BB232A": 40.8, "KXMVESPORTSMULTIGAMEEXTENDED-S202679E54D36704-6CD3A3D04B1": 22.4, "KXMVESPORTSMULTIGAMEEXTENDED-S2026A59B9E2BFC0-A2E4EB84C3F": 7.0, "KXMVECROSSCATEGORY-S2026996A8581109-6BA08E09BEE": 50.0, "KXMVESPORTSMULTIGAMEEXTENDED-S2026A8F219203FD-067DF90C3AD": 7.5, "KXMVECROSSCATEGORY-S20260006EA4F35F-B6CA673E853": 50.0, "KXMVECROSSCATEGORY-S202695F166BCD70-6D3D5CCB8F9": 41.7, "KXMVESPORTSMULTIGAMEEXTENDED-S20265C4B51E6DF6-2260D68955A": 18.5, "KXMVESPORTSMULTIGAMEEXTENDED-S2026C1B1E9DCE53-2E48387E03E": 33.1, "KXMVECROSSCATEGORY-S2026D2E8EA32176-94058154B15": 50.0, "KXMVECROSSCATEGORY-S2026A72C502BED1-8D7F4936EBE": 50.0, "KXMVESPORTSMULTIGAMEEXTENDED-S2026CBCF1DA9391-D25874AEB2A": 18.0, "KXMVESPORTSMULTIGAMEEXTENDED-S20266630A2CA055-025141EF17F": 50.0, "KXMVESPORTSMULTIGAMEEXTENDED-S202650CB1E7C276-D028E64B352": 50.0, "KXMVESPORTSMULTIGAMEEXTENDED-S202603961AF7DF0-96A3E8EC077": 4.5, "KXMVESPORTSMULTIGAMEEXTENDED-S20263AAE63157E5-7FCF3B3C4FB": 50.0, "KXMVECROSSCATEGORY-S2026D21006E1113-E2C70DB71A3": 50.0, "KXMVECROSSCATEGORY-S20267D176E31256-7EE789958F7": 50.0, "KXMVESPORTSMULTIGAMEEXTENDED-S20264AEDE15F58C-B9E755C6786": 50.0, "KXMVECROSSCATEGORY-S2026DE01BD075D2-8B1B8C9AFC1": 1.1, "KXMVESPORTSMULTIGAMEEXTENDED-S20268E59A193242-2892950CA6B": 50.0, "KXMVESPORTSMULTIGAMEEXTENDED-S202629C5D362AA5-0AE5A278758": 25.6, "KXMVESPORTSMULTIGAMEEXTENDED-S2026634339C3375-F160FAEBD3C": 50.0, "KXMVESPORTSMULTIGAMEEXTENDED-S2026F334185A04A-0630AB842CB": 20.1, "KXMVECROSSCATEGORY-S2026264C4F6C1B2-50876EA8EC0": 7.4, "KXMVESPORTSMULTIGAMEEXTENDED-S20266C928168C0F-3B3DEEB5C76": 50.0, "KXMVECROSSCATEGORY-S20265186A60C167-D3DBE6D3E7B": 8.5, "KXMVECROSSCATEGORY-S202677691B34EB6-BAADC7E17EA": 50.0, "KXMVECROSSCATEGORY-S20268A884289E93-B05CA218EF1": 50.0, "KXMVESPORTSMULTIGAMEEXTENDED-S2026F21CDB5107D-ED4D6B2696F": 17.8, "KXMVECROSSCATEGORY-S2026A9C2333A1B8-94098E9E5D5": 50.0, "KXMVECROSSCATEGORY-S202683AED498CA3-34BFA085637": 50.0, "KXMVECROSSCATEGORY-S2026A0E994E452D-D4DFD7617B8": 50.0, "KXMVESPORTSMULTIGAMEEXTENDED-S202676C9AD808E1-D5B792A45D6": 25.5, "KXMVECROSSCATEGORY-S20269B1B9CC5A9B-411E1610EBD": 50.0, "KXMVECROSSCATEGORY-S20265A91F5F1878-15736DEF799": 50.0, "KXMVECROSSCATEGORY-S2026813E45F998B-CFCFEC77C61": 50.0, "KXMVESPORTSMULTIGAMEEXTENDED-S202691F29E66E06-D484FE146B4": 50.0, "KXMVECROSSCATEGORY-S2026008792A66AD-024B3EB8C7C": 50.0, "KXMVESPORTSMULTIGAMEEXTENDED-S2026231039BED1B-44C72A6265A": 50.0, "KXMVECROSSCATEGORY-S2026208103D6531-5FB6CC19645": 33.4, "KXMVESPORTSMULTIGAMEEXTENDED-S2026937A4F9490F-96006F96429": 2.2, "KXMVESPORTSMULTIGAMEEXTENDED-S20266DF314680AF-25A8904B000": 11.4, "KXMVECROSSCATEGORY-S2026A3539059CD0-76B59F3B95B": 5.5, "KXMVECROSSCATEGORY-S20268A884289E93-CA514821012": 50.0, "KXMVESPORTSMULTIGAMEEXTENDED-S202655F60D0A87E-2432A4A3C66": 5.3, "KXMVECROSSCATEGORY-S202693F377C9EAD-231C41A0548": 39.1, "KXMVECROSSCATEGORY-S20262147AE3D76F-95F8B6B9725": 50.0, "KXMVECROSSCATEGORY-S2026390AAD0ED37-4E5F0940FDF": 16.8, "KXMVESPORTSMULTIGAMEEXTENDED-S202610801044638-C844FB84669": 50.0, "KXMVECROSSCATEGORY-S2026BEE8CBD4B16-A86A7B49315": 28.5, "KXMVECROSSCATEGORY-S20260E080CB139D-839D139B5FB": 50.0, "KXMVESPORTSMULTIGAMEEXTENDED-S2026DB077DA9889-40DCE1EDECB": 45.5, "KXMVESPORTSMULTIGAMEEXTENDED-S20263FF8A71612E-0AD65479FB7": 1.8, "KXMVECROSSCATEGORY-S20262D2FBF9D58A-D2735EF9463": 12.3, "KXMVECROSSCATEGORY-S20265BFE897ABDA-B32E426A641": 6.0, "KXMVECROSSCATEGORY-S20269A6BDEF95A6-51D8E216473": 50.0, "KXMVECROSSCATEGORY-S202635D72E4B9D3-5534CEAF990": 50.0, "KXMVECROSSCATEGORY-S20268C5F18A7B75-1465B6B4B73": 3.0, "KXMVECROSSCATEGORY-S2026C28027CD314-802AF8C1C5D": 50.0, "KXMVECROSSCATEGORY-S2026C64A69334A8-B906E53BBEA": 12.2, "KXMVECROSSCATEGORY-S2026323CBBE15C6-C29999E8E0E": 22.4, "KXMVESPORTSMULTIGAMEEXTENDED-S202681FD13ED92C-911E4773B3C": 50.0, "KXMVESPORTSMULTIGAMEEXTENDED-S20264986751D1A8-A0D0DCE52E1": 50.0, "KXMVESPORTSMULTIGAMEEXTENDED-S20265A53E9B8B39-53B57C7BF3F": 50.0, "KXMVECROSSCATEGORY-S20265802D800ED9-973AB426C5E": 12.0, "KXMVESPORTSMULTIGAMEEXTENDED-S2026A17C192C5EC-9772999DB6A": 3.6, "KXMVECROSSCATEGORY-S202667CB004A6B9-DE36720B63E": 50.0, "KXMVESPORTSMULTIGAMEEXTENDED-S2026F43A5404DA8-3B2A4948F07": 11.0, "KXMVESPORTSMULTIGAMEEXTENDED-S20262FB86EB688B-C166D7CE805": 50.0, "KXMVECROSSCATEGORY-S202611ABD2A1273-0D1157DB779": 50.0, "KXMVECROSSCATEGORY-S2026403BB003282-66B3C413367": 9.7, "KXMVESPORTSMULTIGAMEEXTENDED-S2026E2ECFC42226-CFEF1E5F651": 50.0, "KXMVESPORTSMULTIGAMEEXTENDED-S2026937A4F9490F-2C956C351E1": 50.0, "KXMVESPORTSMULTIGAMEEXTENDED-S2026A6E84C54A8D-D11C3E95444": 50.0, "KXMVESPORTSMULTIGAMEEXTENDED-S202669FF8B64482-BFCCF3ABD1E": 50.0, "KXMVECROSSCATEGORY-S20269A67A57F8BA-864BCB634D2": 50.0, "KXMVESPORTSMULTIGAMEEXTENDED-S202697180682C48-0799182BCE5": 50.0, "KXMVESPORTSMULTIGAMEEXTENDED-S20265CCB4724C52-F08CB8688C4": 18.9, "KXMVECROSSCATEGORY-S2026FF7DDA509D9-4AE97797A0F": 50.0, "KXMVESPORTSMULTIGAMEEXTENDED-S20268ED622AB957-8F482972F28": 50.0, "KXMVECROSSCATEGORY-S202610CCC532053-F438834C1DC": 50.0, "KXMVECROSSCATEGORY-S202659ECED5FC48-44AA699338B": 50.0, "KXMVECROSSCATEGORY-S2026B0943432B6C-12A710E1850": 50.0, "KXMVESPORTSMULTIGAMEEXTENDED-S20263E60F1BED39-CA514821012": 15.6, "KXMVECROSSCATEGORY-S202698842F67B0E-C55AD7817BB": 50.0, "KXMVESPORTSMULTIGAMEEXTENDED-S20268AE0C175AA1-744076C3C5D": 3.1, "KXMVECROSSCATEGORY-S20260B79A55D0F1-7AD5AB7CC96": 50.0, "KXMVESPORTSMULTIGAMEEXTENDED-S202613D8F950D53-E90C1A532DC": 50.0, "KXMVECROSSCATEGORY-S2026F733941A5A1-EC36A53DF08": 50.0, "KXMVESPORTSMULTIGAMEEXTENDED-S20260306760EBAB-33A31C1A817": 50.0, "KXMVECROSSCATEGORY-S20268CC6329E11D-A53F1C1DD48": 50.0, "KXMVESPORTSMULTIGAMEEXTENDED-S2026C0874F5708F-30EF4515B0E": 4.5, "KXMVESPORTSMULTIGAMEEXTENDED-S20267AC78499946-19900AE2E69": 12.4, "KXMVECROSSCATEGORY-S20263CBB968D58B-BB0F2FA3D8E": 50.0, "KXMVECROSSCATEGORY-S2026C3B27971D41-A755B721FCC": 3.5, "KXMVESPORTSMULTIGAMEEXTENDED-S2026E4F5D7796B5-EF5B6ABAEA1": 13.0, "KXMVESPORTSMULTIGAMEEXTENDED-S2026D797B0349C0-1109D50BF6C": 50.0, "KXMVESPORTSMULTIGAMEEXTENDED-S2026D345ABF0897-734E15050B5": 49.5, "KXMVECROSSCATEGORY-S2026B22E2EAA14A-A9ADFA008D8": 9.0, "KXMVESPORTSMULTIGAMEEXTENDED-S20267D76A58990B-4DAD273BF7E": 50.0, "KXMVESPORTSMULTIGAMEEXTENDED-S20268A38C489B9A-1EECACD3433": 11.4, "KXMVECROSSCATEGORY-S202646F123D4608-31B9651EE8F": 50.0, "KXMVESPORTSMULTIGAMEEXTENDED-S20264CD2FFD40EB-5D2BDBDB7F2": 50.0, "KXMVECROSSCATEGORY-S20267D3485AD31E-C5D09FD3AB6": 50.0, "KXMVESPORTSMULTIGAMEEXTENDED-S20263B48E5A42A4-9F56F6A2156": 2.9, "KXMVECROSSCATEGORY-S2026DC49DB02EEC-F2E482F455F": 50.0, "KXMVESPORTSMULTIGAMEEXTENDED-S2026B65636A1DA3-EC92E5930AC": 32.5, "KXMVESPORTSMULTIGAMEEXTENDED-S202628E8F21BF8A-E2F58EB0070": 50.0, "KXMVESPORTSMULTIGAMEEXTENDED-S202686EA26F7458-4E017E4E69F": 50.0, "KXMVECROSSCATEGORY-S2026B0943432B6C-ECC415D22B7": 3.1, "KXMVESPORTSMULTIGAMEEXTENDED-S20266B3796EFE66-6037A1A98A7": 50.0, "KXMVESPORTSMULTIGAMEEXTENDED-S2026D6825EE7EDC-0A7470A41A3": 5.0, "KXMVESPORTSMULTIGAMEEXTENDED-S202640D40B1AD4E-E1517730B82": 50.0, "KXMVECROSSCATEGORY-S2026996A8581109-75C571B5923": 30.9, "KXMVECROSSCATEGORY-S20267E0882FB466-13E4406FBAA": 50.0, "KXMVESPORTSMULTIGAMEEXTENDED-S2026062B601B1FF-EB75F62C1E6": 52.0, "KXMVESPORTSMULTIGAMEEXTENDED-S20260061C3950B7-5567C5989DC": 50.0, "KXMVESPORTSMULTIGAMEEXTENDED-S2026C70BC0F44FF-4AC237A9162": 50.0, "KXMVESPORTSMULTIGAMEEXTENDED-S2026F2AB3EE6925-22E36C9D233": 25.3, "KXMVECROSSCATEGORY-S20265C739470D78-A49AA9FADB5": 50.0, "KXMVECROSSCATEGORY-S2026D927B6383A9-66EA9464C50": 18.0, "KXMVESPORTSMULTIGAMEEXTENDED-S20269399A39980C-D8CA414CCDF": 19.9, "KXMVECROSSCATEGORY-S202647380364895-B921996559D": 50.0, "KXMVESPORTSMULTIGAMEEXTENDED-S20266FD6743EED0-B13C5490D60": 1.4, "KXMVESPORTSMULTIGAMEEXTENDED-S20268F39B89E0C9-D90B99FFDB9": 50.0, "KXMVECROSSCATEGORY-S2026775C1749B22-A9C091AF8FD": 31.0, "KXMVESPORTSMULTIGAMEEXTENDED-S2026183F6356CE1-B358477CA6B": 3.0, "KXMVESPORTSMULTIGAMEEXTENDED-S20265961BA1C1F2-C16596B5461": 50.0, "KXMVECROSSCATEGORY-S202635D72E4B9D3-E2F8548BFFF": 50.0, "KXMVESPORTSMULTIGAMEEXTENDED-S2026C126823E2AA-8C87CACC2A7": 50.0, "KXMVESPORTSMULTIGAMEEXTENDED-S20267CECEB9F3E5-7A77B517402": 1.9, "KXMVECROSSCATEGORY-S202618BA21D5B84-D1B12EC5E6C": 2.5, "KXMVESPORTSMULTIGAMEEXTENDED-S20260D67E8A8FB4-6999EEFFD26": 46.9, "KXMVESPORTSMULTIGAMEEXTENDED-S2026F797B44D998-CEAADBCF89E": 50.0, "KXMVESPORTSMULTIGAMEEXTENDED-S2026D6825EE7EDC-8BEC5401353": 4.5, "KXMVESPORTSMULTIGAMEEXTENDED-S2026CC4A30E74B6-48F4AA90C77": 50.0, "KXMVESPORTSMULTIGAMEEXTENDED-S2026F231932D4F2-15B4B826F8E": 16.5, "KXMVECROSSCATEGORY-S2026BB45D1D85E5-34091745A9C": 50.0, "KXMVECROSSCATEGORY-S202677F051FD1CB-15F6F4629CB": 50.0, "KXMVECROSSCATEGORY-S2026C28027CD314-0E252C6EA95": 50.0, "KXMVESPORTSMULTIGAMEEXTENDED-S2026E51C895666F-5C67123FF80": 50.0, "KXMVECROSSCATEGORY-S20267737EAB1CDB-38E0B9391BC": 50.0, "KXMVECROSSCATEGORY-S2026C28027CD314-58C7DA2291D": 50.0, "KXMVECROSSCATEGORY-S2026E64314A35F0-1EC7A5A7365": 50.0, "KXMVESPORTSMULTIGAMEEXTENDED-S2026299EFF0515D-F280BA32EE8": 2.5, "KXMVESPORTSMULTIGAMEEXTENDED-S2026183F6356CE1-3323AA93D04": 50.0, "KXMVESPORTSMULTIGAMEEXTENDED-S2026817041D613B-90937DE4F09": 50.0, "KXMVECROSSCATEGORY-S202677A6E94D7F0-FFE522C3A70": 50.0, "KXMVECROSSCATEGORY-S202683D8208F6B6-0F90BA15F0D": 50.0, "KXMVECROSSCATEGORY-S2026264C4F6C1B2-777870555D8": 50.0, "KXMVESPORTSMULTIGAMEEXTENDED-S2026A9D4F384400-D9A79CC4130": 50.0, "KXMVESPORTSMULTIGAMEEXTENDED-S20261E57C4567AD-F8E31CA7063": 50.0, "KXMVECROSSCATEGORY-S2026940809CE342-ED3DB21C416": 8.3, "KXMVECROSSCATEGORY-S2026B9215BCFFD0-3DD9B879165": 1.4, "KXMVESPORTSMULTIGAMEEXTENDED-S2026F9D54E0FD8C-437812CFC72": 50.0, "KXMVESPORTSMULTIGAMEEXTENDED-S20268785632591A-D5E9443E3D6": 50.0, "KXMVECROSSCATEGORY-S2026AEC5AF657CB-7CE0F209296": 50.0, "KXMVECROSSCATEGORY-S20261E663BF5AF9-975F94E2CF0": 3.5, "KXMVESPORTSMULTIGAMEEXTENDED-S2026985FE74BCE1-6911116AF78": 50.0, "KXMVESPORTSMULTIGAMEEXTENDED-S2026C175EB58BA8-46D51E470F0": 50.0, "KXMVESPORTSMULTIGAMEEXTENDED-S202645372150241-BC0FB1A70E7": 50.0, "KXMVESPORTSMULTIGAMEEXTENDED-S20263CDC2F6D92C-E0DC1AF4A7E": 50.0, "KXMVESPORTSMULTIGAMEEXTENDED-S202629259C37F5B-CD085E55400": 50.0, "KXMVESPORTSMULTIGAMEEXTENDED-S2026D2781F0B1F4-B25573C3FCA": 24.4, "KXMVESPORTSMULTIGAMEEXTENDED-S2026E480690DAA8-D2043450698": 50.0, "KXMVECROSSCATEGORY-S20260B3AF984296-E723761C54C": 50.0, "KXMVESPORTSMULTIGAMEEXTENDED-S2026A9D4F384400-CA561467386": 50.0, "KXMVESPORTSMULTIGAMEEXTENDED-S202645725D7CF2B-484E01B46F2": 46.9, "KXMVECROSSCATEGORY-S2026C8A91491D32-4FDEAF05267": 47.4, "KXMVESPORTSMULTIGAMEEXTENDED-S202687DC78E7F23-EB6C6A806DF": 50.0, "KXMVECROSSCATEGORY-S20264B09B8CDCCC-464A473984F": 50.0, "KXMVECROSSCATEGORY-S2026EF725B66009-08C189AB778": 50.0, "KXMVESPORTSMULTIGAMEEXTENDED-S2026D120CDCF67C-6EE4847741E": 50.0, "KXMVESPORTSMULTIGAMEEXTENDED-S202674DE48AE438-987BE0C5FBD": 1.5, "KXMVECROSSCATEGORY-S2026F088DD7C45B-BD621C00CA8": 50.0, "KXMVESPORTSMULTIGAMEEXTENDED-S2026D3B8E360341-B447628150D": 14.0, "KXMVESPORTSMULTIGAMEEXTENDED-S20266817C54E2D0-C352C10FA07": 50.0, "KXMVESPORTSMULTIGAMEEXTENDED-S20265F02D487E2F-3D69D77A9D1": 50.0, "KXMVECROSSCATEGORY-S202615B5AC5C352-A4F65B70D63": 50.0, "KXMVESPORTSMULTIGAMEEXTENDED-S20265A0BFF6382F-0FAF8B0B646": 4.1, "KXMVECROSSCATEGORY-S2026E31635B1198-8FC6A22AB30": 50.0, "KXMVESPORTSMULTIGAMEEXTENDED-S2026E480690DAA8-A50FD7144C8": 1.3, "KXMVECROSSCATEGORY-S202695DDB9C131C-AD65A1023FB": 59.1, "KXMVESPORTSMULTIGAMEEXTENDED-S202694D5842FF4F-E300FEC2C80": 50.0, "KXMVESPORTSMULTIGAMEEXTENDED-S20261C6B6B8C7C4-4ECDB62A3B6": 9.5, "KXMVECROSSCATEGORY-S2026E12D4B8DBD9-8D2E3E05896": 9.0, "KXMVECROSSCATEGORY-S20262495172F84C-056DDA06D49": 50.0, "KXMVESPORTSMULTIGAMEEXTENDED-S2026A8E2734AF3F-8EDB83F4AD2": 4.5, "KXMVESPORTSMULTIGAMEEXTENDED-S20267B506B6CB03-785BC8D2AD0": 50.0, "KXMVECROSSCATEGORY-S202629CAB097782-21DAE501609": 16.4, "KXMVECROSSCATEGORY-S2026E749163B895-89DDB938EED": 50.0, "KXMVECROSSCATEGORY-S2026A0E994E452D-E5B03636D11": 50.0, "KXMVESPORTSMULTIGAMEEXTENDED-S2026B594214FF20-EE52903B61C": 50.0, "KXMVESPORTSMULTIGAMEEXTENDED-S2026BF029779A5D-F95F4377130": 24.2, "KXMVECROSSCATEGORY-S2026BFF056D901C-361C4071D03": 17.8, "KXMVECROSSCATEGORY-S2026CE869218A3A-800A1A2CC9F": 50.0, "KXMVESPORTSMULTIGAMEEXTENDED-S2026D14ED2199D0-A5239B16A36": 50.0, "KXMVECROSSCATEGORY-S2026BB9AC2B4FB4-32F862F32FC": 50.0, "KXMVESPORTSMULTIGAMEEXTENDED-S2026FF23BCBC4FF-38275EDEB65": 50.0, "KXMVECROSSCATEGORY-S2026C28C9511BB7-FDC4F2828E3": 50.0, "KXMVESPORTSMULTIGAMEEXTENDED-S2026A282F9F8B13-79DFC11C353": 50.0, "KXMVECROSSCATEGORY-S2026E31635B1198-A7D7E249839": 33.8, "KXMVECROSSCATEGORY-S20263B97F40692A-B6628402D67": 50.0, "KXMVECROSSCATEGORY-S2026021A93CC8C8-53E75E1BFE4": 2.0, "KXMVESPORTSMULTIGAMEEXTENDED-S2026D3B8E360341-C8C55A21496": 19.0, "KXMVESPORTSMULTIGAMEEXTENDED-S2026E67109AE779-59C86657874": 50.0, "KXMVESPORTSMULTIGAMEEXTENDED-S20268D02426F023-F8BB9E48EE3": 4.5, "KXMVECROSSCATEGORY-S20268B27A16354F-06B34B519F4": 50.0, "KXMVECROSSCATEGORY-S2026AEDFD100803-C06C773605A": 50.0, "KXMVESPORTSMULTIGAMEEXTENDED-S202628215A75619-BA6059C7E88": 7.0, "KXMVESPORTSMULTIGAMEEXTENDED-S202642BF4A64630-1D0A4D9C840": 50.0, "KXMVECROSSCATEGORY-S2026C9CB67568BA-5BA04CBB30D": 50.0, "KXMVECROSSCATEGORY-S2026B0943432B6C-51669687F17": 3.0, "KXMVECROSSCATEGORY-S20267C1BC9F9ABA-5171E633F6E": 50.0, "KXMVECROSSCATEGORY-S2026F39A7A46704-01FA63CDCDF": 25.9, "KXMVESPORTSMULTIGAMEEXTENDED-S20269399A39980C-B6F880BC977": 50.0, "KXMVESPORTSMULTIGAMEEXTENDED-S202686BE136CB6A-FC6727BAD2E": 50.0, "KXMVESPORTSMULTIGAMEEXTENDED-S2026A282F9F8B13-CD2365F8AE3": 50.0, "KXMVESPORTSMULTIGAMEEXTENDED-S20266A6F7B42C42-49890AED7F2": 50.0, "KXMVESPORTSMULTIGAMEEXTENDED-S20263AD66BAA0D1-D15E9317E67": 50.0, "KXMVESPORTSMULTIGAMEEXTENDED-S2026E9BEBA0B3DC-14FA4F81D63": 22.6, "KXMVECROSSCATEGORY-S20261E74F54ACA2-4B0EB03A258": 50.0, "KXMVESPORTSMULTIGAMEEXTENDED-S202658AA9322B7F-7EA72E793A7": 6.9, "KXMVECROSSCATEGORY-S2026580E612E0F8-A9FB623376D": 1.3, "KXMVESPORTSMULTIGAMEEXTENDED-S202648A3F07C4A7-2473AF09F75": 50.0, "KXMVECROSSCATEGORY-S2026BCCC82E86D6-1678F8BF769": 7.0, "KXMVESPORTSMULTIGAMEEXTENDED-S20264B9DD8F3DDB-6E0841D7DB7": 50.0, "KXMVECROSSCATEGORY-S2026CD5BEE152E3-42CCDD83F0E": 50.0, "KXMVESPORTSMULTIGAMEEXTENDED-S2026F8636CA996E-6AB5DE004DF": 4.5, "KXMVECROSSCATEGORY-S2026996A8581109-54AEFBF6C4B": 50.0, "KXMVESPORTSMULTIGAMEEXTENDED-S2026AEF909C1456-6AE11378941": 50.0, "KXMVECROSSCATEGORY-S2026078B0A21F71-F2229914EB3": 50.0, "KXMVECROSSCATEGORY-S202615B5AC5C352-A9983BE9988": 59.8, "KXMVESPORTSMULTIGAMEEXTENDED-S20266E8FC772EDB-781D852F094": 50.0, "KXMVECROSSCATEGORY-S20265E10723855E-5FD9CC14CC8": 50.0, "KXMVECROSSCATEGORY-S2026A62A8E025AD-F22620120C0": 13.0, "KXMVESPORTSMULTIGAMEEXTENDED-S2026D3B8E360341-A397F4A7C66": 12.0, "KXMVESPORTSMULTIGAMEEXTENDED-S202601477381B7C-2D6EBA4BC4D": 50.0, "KXMVESPORTSMULTIGAMEEXTENDED-S2026F8636CA996E-413F67C32B5": 50.0, "KXMVECROSSCATEGORY-S20268EDC43484AA-1531337EC2D": 10.0, "KXMVECROSSCATEGORY-S2026B8FF521CA9D-353C69B3256": 50.0, "KXMVECROSSCATEGORY-S2026A0AC62EDF80-159BD7CEF26": 50.0, "KXMVECROSSCATEGORY-S2026DF086789B15-B252798D77B": 50.0, "KXMVESPORTSMULTIGAMEEXTENDED-S2026BEE2B4CC638-D39168C7877": 50.0, "KXMVECROSSCATEGORY-S20267A72C2C13AC-F043D32E967": 50.0, "KXMVECROSSCATEGORY-S20265B50BD4043B-5D32F7EBBB0": 50.0, "KXMVECROSSCATEGORY-S20260C38460085C-FDF1F960FA2": 50.0, "KXMVESPORTSMULTIGAMEEXTENDED-S2026A018F6147E9-A199645B3C5": 13.5, "KXMVESPORTSMULTIGAMEEXTENDED-S20263399F121109-70421BCF7F1": 39.1, "KXMVESPORTSMULTIGAMEEXTENDED-S2026D14ED2199D0-22DA4F4BA23": 50.0, "KXMVECROSSCATEGORY-S20261AE94309FC1-D54A4BEC7F3": 50.0, "KXMVECROSSCATEGORY-S20269582DDD26EB-D16D85940F0": 50.0, "KXMVESPORTSMULTIGAMEEXTENDED-S2026E2F242DD5A7-AF655FB531B": 50.0, "KXMVESPORTSMULTIGAMEEXTENDED-S202615BDE7B7956-DBB454B9800": 50.0, "KXMVECROSSCATEGORY-S20265FA3D4020D7-462DD560B4B": 50.0, "KXMVESPORTSMULTIGAMEEXTENDED-S2026D3B8E360341-F1E40357865": 12.0, "KXMVECROSSCATEGORY-S2026EF11021174D-34E077A383C": 50.0, "KXMVESPORTSMULTIGAMEEXTENDED-S2026DAAA84ADBF6-6843C3D1A5D": 50.0, "KXMVESPORTSMULTIGAMEEXTENDED-S20263F4A78A6317-4787E5A1DB6": 4.0, "KXMVESPORTSMULTIGAMEEXTENDED-S20268971EB59AA8-9F75CEC1FA9": 50.0, "KXMVECROSSCATEGORY-S2026DEB223CDB3C-C8AA0096AD5": 50.0, "KXMVECROSSCATEGORY-S202668BAA4363C4-C5DABD8D5A5": 50.0, "KXMVESPORTSMULTIGAMEEXTENDED-S20262419EA8C598-DB17B36901B": 4.2, "KXMVESPORTSMULTIGAMEEXTENDED-S202641674607D5C-C94851C70A5": 50.0, "KXMVESPORTSMULTIGAMEEXTENDED-S2026C5EFDA98E59-7DEE1AAE0CE": 50.0, "KXMVESPORTSMULTIGAMEEXTENDED-S2026997A151B5A9-58CB97FE611": 50.0, "KXMVECROSSCATEGORY-S2026C28027CD314-884F6E9CC33": 50.0, "KXMVECROSSCATEGORY-S20262E03D1D25E3-7E7A9C765BA": 50.0, "KXMVESPORTSMULTIGAMEEXTENDED-S202642BF4A64630-42473577606": 50.0, "KXMVECROSSCATEGORY-S20265BD20D30144-950DC70F6D5": 50.0, "KXMVESPORTSMULTIGAMEEXTENDED-S2026406B2E36EC7-5E9FA804814": 50.0, "KXMVESPORTSMULTIGAMEEXTENDED-S2026F8636CA996E-C01D51DF7C6": 50.0, "KXMVESPORTSMULTIGAMEEXTENDED-S202687DC78E7F23-A5857A23F5A": 50.0, "KXMVECROSSCATEGORY-S2026F5D165D51F4-7B34ACD1DA8": 50.0, "KXMVECROSSCATEGORY-S20261A5DB3968D1-3B4BAA95B41": 50.0, "KXMVESPORTSMULTIGAMEEXTENDED-S202629A72B8F88A-809FB2AAE8E": 50.0, "KXMVESPORTSMULTIGAMEEXTENDED-S2026A94024A6576-3F64A559CFE": 8.0, "KXMVECROSSCATEGORY-S202691773971099-5D40403CF2C": 50.0, "KXMVESPORTSMULTIGAMEEXTENDED-S20264AEDE15F58C-1452A195A78": 50.0, "KXMVECROSSCATEGORY-S2026622A70327E3-DE666F89B48": 50.0, "KXMVECROSSCATEGORY-S2026AF80C56DC27-4F7ADF07EC0": 50.0, "KXMVESPORTSMULTIGAMEEXTENDED-S20269D0AF0E58DF-DE32F3E2C59": 23.5, "KXMVECROSSCATEGORY-S202623F777FA5D8-B2D1896DA66": 50.0, "KXMVECROSSCATEGORY-S20268EA54B3560C-4F80C2E1F3B": 7.5, "KXMVESPORTSMULTIGAMEEXTENDED-S202616A12781945-4FAA61EAC61": 66.3, "KXMVECROSSCATEGORY-S2026886A1E3EB60-91AEB76106F": 50.0, "KXMVECROSSCATEGORY-S20262AA5FF0341D-57A2F5D713A": 50.0, "KXMVESPORTSMULTIGAMEEXTENDED-S202686EA26F7458-5688C454B48": 50.0, "KXMVECROSSCATEGORY-S20268B1FAC71376-E3FEE4B78D9": 50.0, "KXMVESPORTSMULTIGAMEEXTENDED-S2026225FE24F843-9805F06A9F0": 50.0, "KXMVECROSSCATEGORY-S2026996A8581109-AA551A6F5A9": 50.0, "KXMVESPORTSMULTIGAMEEXTENDED-S20263399643EA74-3B62A2DD55F": 50.0, "KXMVESPORTSMULTIGAMEEXTENDED-S202678D8C43D213-28A86D21CFC": 50.0, "KXMVESPORTSMULTIGAMEEXTENDED-S2026D7A63F97DD2-8610CFF7737": 50.0, "KXMVECROSSCATEGORY-S2026EE3DB97A33B-2C985D67B87": 50.0}